[
  {
    "category_slug": "xe-may-dien",
    "product": {
      "name": "XE MÁY ĐIỆN DIBAO PANSY S3",
      "slug": "xe-máy-điện-dibao-pansy-s3",
      "description": "Tốc độ: 50 km/h | Công suất: 350 W | ắc quy 60v (5x12v) 22ah\n8\ntôc độ tối đa\n45-50km/h\n9\nquãng đường đi/lần xạc\n60-90km (tùy thuộc vào tốc độ di chuyển và tải trọng)\n10\nlốp xe\nlốp không săm 3",
      "price": 1299000013990000.0,
      "discount_price": null,
      "stock_quantity": 40,
      "rating": 0,
      "review_count": 0,
      "is_featured": false,
      "is_active": true
    },
    "images": [
      {
        "image_url": "19e891f7-4fc6-40e4-aa6b-5e25591725f4.jpg",
        "alt_text": "XE MÁY ĐIỆN DIBAO PANSY S3",
        "sort_order": 0,
        "is_primary": true
      },
      {
        "image_url": "343e7a53-e8ab-4e92-b0f5-1dbf291c181e.jpg",
        "alt_text": "XE MÁY ĐIỆN DIBAO PANSY S3",
        "sort_order": 1,
        "is_primary": false
      },
      {
        "image_url": "eea9aeb6-63af-4bb7-b09e-52c6231ddcfb.jpg",
        "alt_text": "XE MÁY ĐIỆN DIBAO PANSY S3",
        "sort_order": 2,
        "is_primary": false
      },
      {
        "image_url": "3904e7c3-7aa1-4bdb-913f-7df5fc024d30.jpg",
        "alt_text": "XE MÁY ĐIỆN DIBAO PANSY S3",
        "sort_order": 3,
        "is_primary": false
      },
      {
        "image_url": "5f1d3c59-3dfb-4896-8497-98a67eba8f3a.jpg",
        "alt_text": "XE MÁY ĐIỆN DIBAO PANSY S3",
        "sort_order": 4,
        "is_primary": false
      }
    ],
    "variants": [
      {
        "sku": "xe-máy-điện-dibao-pansy-s3-default",
        "color": "",
        "size": "",
        "stock_quantity": 20
      }
    ]
  },
  {
    "category_slug": "xe-may-dien",
    "product": {
      "name": "XE MÁY ĐIỆN DIBAO PANSY S2 (CÀNG NHÔM)",
      "slug": "xe-máy-điện-dibao-pansy-s2-càng-nhôm",
      "description": "Tốc độ: 50 km/h | Công suất: 450 W | ắc quy 60v (5x12v) 22ah\n7\ntôc độ tối đa\n45-50km/h\n8\nquãng đường đi/lần xạc\n60-100km (tùy theo tốc độ di chuyển và tải trọng)\n9\nlốp xe\nlốp không săm 90/90-10\n10\nkiểu phanh\nphanh đĩa trước",
      "price": 1299000013990000.0,
      "discount_price": null,
      "stock_quantity": 40,
      "rating": 0,
      "review_count": 0,
      "is_featured": false,
      "is_active": true
    },
    "images": [
      {
        "image_url": "82890eca-d821-4bbd-8d9f-917b0ece36bd.jpg",
        "alt_text": "XE MÁY ĐIỆN DIBAO PANSY S2 (CÀNG NHÔM)",
        "sort_order": 0,
        "is_primary": true
      },
      {
        "image_url": "a0fa486c-c387-4628-a1dc-8729aeb88fba.jpg",
        "alt_text": "XE MÁY ĐIỆN DIBAO PANSY S2 (CÀNG NHÔM)",
        "sort_order": 1,
        "is_primary": false
      },
      {
        "image_url": "8f1b904f-bca5-4e9b-9938-401d088a5af7.jpg",
        "alt_text": "XE MÁY ĐIỆN DIBAO PANSY S2 (CÀNG NHÔM)",
        "sort_order": 2,
        "is_primary": false
      },
      {
        "image_url": "9414aaef-3754-43c0-8520-e1073013baf3.jpg",
        "alt_text": "XE MÁY ĐIỆN DIBAO PANSY S2 (CÀNG NHÔM)",
        "sort_order": 3,
        "is_primary": false
      },
      {
        "image_url": "69d51693-8094-4608-85cd-5004196f1d4f.jpg",
        "alt_text": "XE MÁY ĐIỆN DIBAO PANSY S2 (CÀNG NHÔM)",
        "sort_order": 4,
        "is_primary": false
      }
    ],
    "variants": [
      {
        "sku": "xe-máy-điện-dibao-pansy-s2-càng-nhôm-default",
        "color": "",
        "size": "",
        "stock_quantity": 20
      }
    ]
  },
  {
    "category_slug": "xe-may-dien",
    "product": {
      "name": "XE MÁY ĐIỆN DIBAO PANSY S4",
      "slug": "xe-máy-điện-dibao-pansy-s4",
      "description": "Tốc độ: 50 km/h | Công suất: 350 W | ắc quy 60v (5x12v) 22ah\n7\ntôc độ tối đa\n45-50km/h\n8\nquãng đường đi/lần xạc\n60-90km (tùy thuộc vào tốc độ di chuyển và tải trọng)\n9\nlốp xe\nlốp không săm 3",
      "price": 1299000013990000.0,
      "discount_price": null,
      "stock_quantity": 40,
      "rating": 0,
      "review_count": 0,
      "is_featured": false,
      "is_active": true
    },
    "images": [
      {
        "image_url": "ae275676-83b2-44d3-81a7-57f7b14a6313.jpg",
        "alt_text": "XE MÁY ĐIỆN DIBAO PANSY S4",
        "sort_order": 0,
        "is_primary": true
      },
      {
        "image_url": "acfd6537-6f3c-4a7b-96f5-5439df4f7e8a.jpg",
        "alt_text": "XE MÁY ĐIỆN DIBAO PANSY S4",
        "sort_order": 1,
        "is_primary": false
      },
      {
        "image_url": "7d6cfddc-c443-4caa-9396-72db02685083.jpg",
        "alt_text": "XE MÁY ĐIỆN DIBAO PANSY S4",
        "sort_order": 2,
        "is_primary": false
      },
      {
        "image_url": "aeec314a-8160-467c-a943-072a9d635ed9.jpg",
        "alt_text": "XE MÁY ĐIỆN DIBAO PANSY S4",
        "sort_order": 3,
        "is_primary": false
      },
      {
        "image_url": "399106f6-4250-42d4-a404-0f8fe5b8accd.jpg",
        "alt_text": "XE MÁY ĐIỆN DIBAO PANSY S4",
        "sort_order": 4,
        "is_primary": false
      }
    ],
    "variants": [
      {
        "sku": "xe-máy-điện-dibao-pansy-s4-default",
        "color": "",
        "size": "",
        "stock_quantity": 20
      }
    ]
  },
  {
    "category_slug": "xe-may-dien",
    "product": {
      "name": "XE MÁY ĐIỆN DIBAO CREER NILE",
      "slug": "xe-máy-điện-dibao-creer-nile",
      "description": "Tốc độ: 50 km/h | Công suất: 400 W | ắc quy chì a xít 60v (5x12v) 23ah\n7\ntôc độ tối đa:\n40-50km/h\n8\nquãng đường đi/lần xạc:\n60-90km (tùy thuộc vào tốc độ di chuyển và tải trọng)\n9\nlốp xe:\nlốp không săm 90/90-10\n10\nkiểu phanh:\nphanh đĩa trước",
      "price": 1299000013990000.0,
      "discount_price": null,
      "stock_quantity": 40,
      "rating": 0,
      "review_count": 0,
      "is_featured": false,
      "is_active": true
    },
    "images": [
      {
        "image_url": "dac05f34-ab06-405f-87e6-7bb3e6030157.jpg",
        "alt_text": "XE MÁY ĐIỆN DIBAO CREER NILE",
        "sort_order": 0,
        "is_primary": true
      },
      {
        "image_url": "5bba8f69-24ac-4e1d-91a8-0b4437d36b98.jpg",
        "alt_text": "XE MÁY ĐIỆN DIBAO CREER NILE",
        "sort_order": 1,
        "is_primary": false
      },
      {
        "image_url": "5bcfd086-66f0-48f6-a286-b40ed060d6ff.jpg",
        "alt_text": "XE MÁY ĐIỆN DIBAO CREER NILE",
        "sort_order": 2,
        "is_primary": false
      },
      {
        "image_url": "6300bd76-4a0d-4eac-8cdc-906c372cf993.jpg",
        "alt_text": "XE MÁY ĐIỆN DIBAO CREER NILE",
        "sort_order": 3,
        "is_primary": false
      },
      {
        "image_url": "e724614e-9a04-4159-9115-0072d40db82a.jpg",
        "alt_text": "XE MÁY ĐIỆN DIBAO CREER NILE",
        "sort_order": 4,
        "is_primary": false
      }
    ],
    "variants": [
      {
        "sku": "xe-máy-điện-dibao-creer-nile-default",
        "color": "",
        "size": "",
        "stock_quantity": 20
      }
    ]
  },
  {
    "category_slug": "xe-may-dien",
    "product": {
      "name": "XE MÁY ĐIỆN DIBAO PANSY DIO",
      "slug": "xe-máy-điện-dibao-pansy-dio",
      "description": "Tốc độ: 55 km/h | Công suất: 450 W | ắc quy 60v (5x12v) 22ah\n6 tôc độ 45-55km/h\n7 quãng đường đi/lần xạc 60km -90km (tùy theo tốc độ và tải trọng)\n8 lốp xe lốp không săm 90/90-10\n9 kiểu phanh phanh đĩa trước",
      "price": 1299000013990000.0,
      "discount_price": null,
      "stock_quantity": 40,
      "rating": 0,
      "review_count": 0,
      "is_featured": false,
      "is_active": true
    },
    "images": [
      {
        "image_url": "c22ce4fc-3815-4712-a356-b7ccfdb72e89.jpg",
        "alt_text": "XE MÁY ĐIỆN DIBAO PANSY DIO",
        "sort_order": 0,
        "is_primary": true
      },
      {
        "image_url": "f0c2da63-9fc4-4a32-b536-325c73d69e6e.jpg",
        "alt_text": "XE MÁY ĐIỆN DIBAO PANSY DIO",
        "sort_order": 1,
        "is_primary": false
      },
      {
        "image_url": "be4c15ea-44cf-4e20-9b63-c07de779d4b3.jpg",
        "alt_text": "XE MÁY ĐIỆN DIBAO PANSY DIO",
        "sort_order": 2,
        "is_primary": false
      },
      {
        "image_url": "6816b271-1dc5-41d8-8152-9f76585e24f8.jpg",
        "alt_text": "XE MÁY ĐIỆN DIBAO PANSY DIO",
        "sort_order": 3,
        "is_primary": false
      },
      {
        "image_url": "9cde5306-8091-4a9b-bd33-119ff9c15c13.jpg",
        "alt_text": "XE MÁY ĐIỆN DIBAO PANSY DIO",
        "sort_order": 4,
        "is_primary": false
      }
    ],
    "variants": [
      {
        "sku": "xe-máy-điện-dibao-pansy-dio-default",
        "color": "",
        "size": "",
        "stock_quantity": 20
      }
    ]
  },
  {
    "category_slug": "xe-may-dien",
    "product": {
      "name": "XE MÁY ĐIỆN DIBAO TESLA DIO",
      "slug": "xe-máy-điện-dibao-tesla-dio",
      "description": "Tốc độ: 50 km/h | Công suất: 450 W | ắc quy 60v (5x12v) 22ah\n7 tôc độ 45-50km/h\n8 quãng đường đi/lần xạc 60km -90km (tùy theo tốc độ và tải trọng)\n9 lốp xe lốp không săm 90/90-10\n10 kiểu phanh phanh đĩa trước",
      "price": 1299000013990000.0,
      "discount_price": null,
      "stock_quantity": 40,
      "rating": 0,
      "review_count": 0,
      "is_featured": false,
      "is_active": true
    },
    "images": [
      {
        "image_url": "488b933d-cf0e-47e8-ac3f-094e46ef6f8c.jpg",
        "alt_text": "XE MÁY ĐIỆN DIBAO TESLA DIO",
        "sort_order": 0,
        "is_primary": true
      },
      {
        "image_url": "93fef053-6996-4cd5-81bd-84f023aeca2f.jpg",
        "alt_text": "XE MÁY ĐIỆN DIBAO TESLA DIO",
        "sort_order": 1,
        "is_primary": false
      },
      {
        "image_url": "2336e388-9f46-4c05-9617-a80dbcc37c2a.jpg",
        "alt_text": "XE MÁY ĐIỆN DIBAO TESLA DIO",
        "sort_order": 2,
        "is_primary": false
      },
      {
        "image_url": "c170b648-dc66-4010-ae97-0eb8db9fab05.jpg",
        "alt_text": "XE MÁY ĐIỆN DIBAO TESLA DIO",
        "sort_order": 3,
        "is_primary": false
      },
      {
        "image_url": "f7d9eb27-b7f9-4f13-8072-e2abffd8a25e.jpg",
        "alt_text": "XE MÁY ĐIỆN DIBAO TESLA DIO",
        "sort_order": 4,
        "is_primary": false
      }
    ],
    "variants": [
      {
        "sku": "xe-máy-điện-dibao-tesla-dio-default",
        "color": "",
        "size": "",
        "stock_quantity": 20
      }
    ]
  },
  {
    "category_slug": "xe-may-dien",
    "product": {
      "name": "XE MÁY ĐIỆN DIBAO RS 50CC",
      "slug": "xe-máy-điện-dibao-rs-50cc",
      "description": "Công suất: 100 W",
      "price": 1519000017590000.0,
      "discount_price": null,
      "stock_quantity": 40,
      "rating": 0,
      "review_count": 0,
      "is_featured": false,
      "is_active": true
    },
    "images": [
      {
        "image_url": "95563ea7-ffc7-47ee-90c8-333dff717d70.jpg",
        "alt_text": "XE MÁY ĐIỆN DIBAO RS 50CC",
        "sort_order": 0,
        "is_primary": true
      },
      {
        "image_url": "ad5d41b8-73c8-4d9f-b9c8-5717300bedfd.jpg",
        "alt_text": "XE MÁY ĐIỆN DIBAO RS 50CC",
        "sort_order": 1,
        "is_primary": false
      },
      {
        "image_url": "fc44f293-f10a-468f-b54b-414f7dcdf3a7.jpg",
        "alt_text": "XE MÁY ĐIỆN DIBAO RS 50CC",
        "sort_order": 2,
        "is_primary": false
      },
      {
        "image_url": "a2a8f2d6-b7ef-4b11-b721-d396c58be44f.jpg",
        "alt_text": "XE MÁY ĐIỆN DIBAO RS 50CC",
        "sort_order": 3,
        "is_primary": false
      },
      {
        "image_url": "8dfee691-fd3c-4fc3-9b4e-7a722a70fc6e.jpg",
        "alt_text": "XE MÁY ĐIỆN DIBAO RS 50CC",
        "sort_order": 4,
        "is_primary": false
      }
    ],
    "variants": [
      {
        "sku": "xe-máy-điện-dibao-rs-50cc-default",
        "color": "",
        "size": "",
        "stock_quantity": 20
      }
    ]
  },
  {
    "category_slug": "xe-may-dien",
    "product": {
      "name": "XE MÁY DIBAO SIR 50CC",
      "slug": "xe-máy-dibao-sir-50cc",
      "description": "Công suất: 100 W",
      "price": 1499000017390000.0,
      "discount_price": null,
      "stock_quantity": 40,
      "rating": 0,
      "review_count": 0,
      "is_featured": false,
      "is_active": true
    },
    "images": [
      {
        "image_url": "bfd9aab4-e317-4f21-944d-f840064220aa.jpg",
        "alt_text": "XE MÁY DIBAO SIR 50CC",
        "sort_order": 0,
        "is_primary": true
      },
      {
        "image_url": "ab2f0b60-3897-4349-85ac-62a24345e7ae.jpg",
        "alt_text": "XE MÁY DIBAO SIR 50CC",
        "sort_order": 1,
        "is_primary": false
      },
      {
        "image_url": "50b8c284-a9ac-47a9-bfbd-27e0756aac97.jpg",
        "alt_text": "XE MÁY DIBAO SIR 50CC",
        "sort_order": 2,
        "is_primary": false
      },
      {
        "image_url": "2c6106cf-3a01-48d6-ba45-887fbb1a1bbd.jpg",
        "alt_text": "XE MÁY DIBAO SIR 50CC",
        "sort_order": 3,
        "is_primary": false
      },
      {
        "image_url": "023e191e-9936-4aa6-9d60-fe682124e409.jpg",
        "alt_text": "XE MÁY DIBAO SIR 50CC",
        "sort_order": 4,
        "is_primary": false
      }
    ],
    "variants": [
      {
        "sku": "xe-máy-dibao-sir-50cc-default",
        "color": "",
        "size": "",
        "stock_quantity": 20
      }
    ]
  },
  {
    "category_slug": "xe-may-dien",
    "product": {
      "name": "XE MÁY TAY GA 50CC DIBAO CREER",
      "slug": "xe-máy-tay-ga-50cc-dibao-creer",
      "description": "Công suất: 600 W",
      "price": 1945000021690000.0,
      "discount_price": null,
      "stock_quantity": 40,
      "rating": 0,
      "review_count": 0,
      "is_featured": false,
      "is_active": true
    },
    "images": [
      {
        "image_url": "492551ac-4e00-4c34-a5a5-f5c0d1877743.jpg",
        "alt_text": "XE MÁY TAY GA 50CC DIBAO CREER",
        "sort_order": 0,
        "is_primary": true
      },
      {
        "image_url": "74a6265a-56fe-4ce3-a2dd-ad5a360a41ae.jpg",
        "alt_text": "XE MÁY TAY GA 50CC DIBAO CREER",
        "sort_order": 1,
        "is_primary": false
      },
      {
        "image_url": "34eb8578-2d29-4874-a672-2a5a38cd3335.jpg",
        "alt_text": "XE MÁY TAY GA 50CC DIBAO CREER",
        "sort_order": 2,
        "is_primary": false
      },
      {
        "image_url": "5598a13b-3178-4037-9869-6556313f4968.jpg",
        "alt_text": "XE MÁY TAY GA 50CC DIBAO CREER",
        "sort_order": 3,
        "is_primary": false
      },
      {
        "image_url": "87e0b960-2ae3-41f7-90b1-04dec1be5943.jpg",
        "alt_text": "XE MÁY TAY GA 50CC DIBAO CREER",
        "sort_order": 4,
        "is_primary": false
      }
    ],
    "variants": [
      {
        "sku": "xe-máy-tay-ga-50cc-dibao-creer-default",
        "color": "",
        "size": "",
        "stock_quantity": 20
      }
    ]
  },
  {
    "category_slug": "xe-may-dien",
    "product": {
      "name": "XE MÁY TAY GA 50CC DIBAO PANSY XS1 (BẢN NÂNG CẤP)",
      "slug": "xe-máy-tay-ga-50cc-dibao-pansy-xs1-bản-nâng-cấp",
      "description": "Công suất: 600 W",
      "price": 1945000021690000.0,
      "discount_price": null,
      "stock_quantity": 40,
      "rating": 0,
      "review_count": 0,
      "is_featured": false,
      "is_active": true
    },
    "images": [
      {
        "image_url": "044be135-3814-4c3e-8e04-32b47664e588.jpg",
        "alt_text": "XE MÁY TAY GA 50CC DIBAO PANSY XS1 (BẢN NÂNG CẤP)",
        "sort_order": 0,
        "is_primary": true
      },
      {
        "image_url": "aee21b05-b96d-47fe-8b42-6995f2b68aa5.jpg",
        "alt_text": "XE MÁY TAY GA 50CC DIBAO PANSY XS1 (BẢN NÂNG CẤP)",
        "sort_order": 1,
        "is_primary": false
      },
      {
        "image_url": "2a9ed70a-a108-41ac-8965-c995fb0d548c.jpg",
        "alt_text": "XE MÁY TAY GA 50CC DIBAO PANSY XS1 (BẢN NÂNG CẤP)",
        "sort_order": 2,
        "is_primary": false
      },
      {
        "image_url": "f0b5ba90-6b47-4dfb-b187-a39c54a5c74b.jpg",
        "alt_text": "XE MÁY TAY GA 50CC DIBAO PANSY XS1 (BẢN NÂNG CẤP)",
        "sort_order": 3,
        "is_primary": false
      },
      {
        "image_url": "b589b9cc-0b17-47d0-9f56-a6c5a96daa28.jpg",
        "alt_text": "XE MÁY TAY GA 50CC DIBAO PANSY XS1 (BẢN NÂNG CẤP)",
        "sort_order": 4,
        "is_primary": false
      }
    ],
    "variants": [
      {
        "sku": "xe-máy-tay-ga-50cc-dibao-pansy-xs1-bản-nâng-cấp-default",
        "color": "",
        "size": "",
        "stock_quantity": 20
      }
    ]
  },
  {
    "category_slug": "xe-may-dien",
    "product": {
      "name": "Xe tay ga 50cc DIBAO Tesla X",
      "slug": "xe-tay-ga-50cc-dibao-tesla-x",
      "description": "",
      "price": 2639000026990000.0,
      "discount_price": null,
      "stock_quantity": 40,
      "rating": 0,
      "review_count": 0,
      "is_featured": false,
      "is_active": true
    },
    "images": [
      {
        "image_url": "31a9a3d8-40fc-47b1-ae4c-cd8dab95f8c4.jpg",
        "alt_text": "Xe tay ga 50cc DIBAO Tesla X",
        "sort_order": 0,
        "is_primary": true
      },
      {
        "image_url": "b49814ed-e554-4d17-adda-2abf5ecd54cb.jpg",
        "alt_text": "Xe tay ga 50cc DIBAO Tesla X",
        "sort_order": 1,
        "is_primary": false
      },
      {
        "image_url": "6b785ddf-a8f2-4dfa-940b-1b3336a87c73.jpg",
        "alt_text": "Xe tay ga 50cc DIBAO Tesla X",
        "sort_order": 2,
        "is_primary": false
      },
      {
        "image_url": "727428f8-2609-4c9e-b085-8ebf65304992.jpg",
        "alt_text": "Xe tay ga 50cc DIBAO Tesla X",
        "sort_order": 3,
        "is_primary": false
      },
      {
        "image_url": "c1de5edf-e83c-442e-8285-435d7407c886.jpg",
        "alt_text": "Xe tay ga 50cc DIBAO Tesla X",
        "sort_order": 4,
        "is_primary": false
      }
    ],
    "variants": [
      {
        "sku": "xe-tay-ga-50cc-dibao-tesla-x-default",
        "color": "",
        "size": "",
        "stock_quantity": 20
      }
    ]
  },
  {
    "category_slug": "xe-may-dien",
    "product": {
      "name": "XE MÁY TAY GA DIBAO PANSY XS1",
      "slug": "xe-máy-tay-ga-dibao-pansy-xs1",
      "description": "Công suất: 600 W",
      "price": 1945000021690000.0,
      "discount_price": null,
      "stock_quantity": 40,
      "rating": 0,
      "review_count": 0,
      "is_featured": false,
      "is_active": true
    },
    "images": [
      {
        "image_url": "cdb5194a-ce59-4de2-b77f-1b8426cebb7f.jpg",
        "alt_text": "XE MÁY TAY GA DIBAO PANSY XS1",
        "sort_order": 0,
        "is_primary": true
      },
      {
        "image_url": "260cdf26-1bb6-49d1-8faa-a079fcafcccb.jpg",
        "alt_text": "XE MÁY TAY GA DIBAO PANSY XS1",
        "sort_order": 1,
        "is_primary": false
      },
      {
        "image_url": "88b9edeb-9e35-4e79-af52-7941c8efa1e3.jpg",
        "alt_text": "XE MÁY TAY GA DIBAO PANSY XS1",
        "sort_order": 2,
        "is_primary": false
      },
      {
        "image_url": "7d0fd502-9189-451a-bc55-ae8a49690475.jpg",
        "alt_text": "XE MÁY TAY GA DIBAO PANSY XS1",
        "sort_order": 3,
        "is_primary": false
      },
      {
        "image_url": "e82e6286-35c8-424b-8953-94af3dce6771.jpg",
        "alt_text": "XE MÁY TAY GA DIBAO PANSY XS1",
        "sort_order": 4,
        "is_primary": false
      }
    ],
    "variants": [
      {
        "sku": "xe-máy-tay-ga-dibao-pansy-xs1-default",
        "color": "",
        "size": "",
        "stock_quantity": 20
      }
    ]
  },
  {
    "category_slug": "xe-may-dien",
    "product": {
      "name": "XE MÁY TAY GA DIBAO PANSY XS",
      "slug": "xe-máy-tay-ga-dibao-pansy-xs",
      "description": "Công suất: 600 W",
      "price": 1945000021690000.0,
      "discount_price": null,
      "stock_quantity": 40,
      "rating": 0,
      "review_count": 0,
      "is_featured": false,
      "is_active": true
    },
    "images": [
      {
        "image_url": "a97abbcd-0c68-4974-9270-d4f1b579907c.jpg",
        "alt_text": "XE MÁY TAY GA DIBAO PANSY XS",
        "sort_order": 0,
        "is_primary": true
      },
      {
        "image_url": "785d394f-4630-46bb-b85a-4f6a7b2322d3.jpg",
        "alt_text": "XE MÁY TAY GA DIBAO PANSY XS",
        "sort_order": 1,
        "is_primary": false
      },
      {
        "image_url": "67eb2a14-99e7-4e89-97e6-d904075455c8.jpg",
        "alt_text": "XE MÁY TAY GA DIBAO PANSY XS",
        "sort_order": 2,
        "is_primary": false
      },
      {
        "image_url": "301708d8-8e62-4def-a4ef-613f682145a3.jpg",
        "alt_text": "XE MÁY TAY GA DIBAO PANSY XS",
        "sort_order": 3,
        "is_primary": false
      },
      {
        "image_url": "2a1635a6-1c0d-42d6-8da5-fa67e0d5e124.jpg",
        "alt_text": "XE MÁY TAY GA DIBAO PANSY XS",
        "sort_order": 4,
        "is_primary": false
      }
    ],
    "variants": [
      {
        "sku": "xe-máy-tay-ga-dibao-pansy-xs-default",
        "color": "",
        "size": "",
        "stock_quantity": 20
      }
    ]
  },
  {
    "category_slug": "xe-may-dien",
    "product": {
      "name": "XE MÁY TAY GA 50CC DIBAO GOFAST",
      "slug": "xe-máy-tay-ga-50cc-dibao-gofast",
      "description": "Công suất: 200 W",
      "price": 1945000021690000.0,
      "discount_price": null,
      "stock_quantity": 40,
      "rating": 0,
      "review_count": 0,
      "is_featured": false,
      "is_active": true
    },
    "images": [
      {
        "image_url": "20f16c3e-368e-4fac-ae15-3a4477848c95.jpg",
        "alt_text": "XE MÁY TAY GA 50CC DIBAO GOFAST",
        "sort_order": 0,
        "is_primary": true
      },
      {
        "image_url": "1a827129-5cb8-41be-8aab-3612b4af8b72.jpg",
        "alt_text": "XE MÁY TAY GA 50CC DIBAO GOFAST",
        "sort_order": 1,
        "is_primary": false
      },
      {
        "image_url": "947ceecf-f14f-4138-a49a-edf0531150a9.jpg",
        "alt_text": "XE MÁY TAY GA 50CC DIBAO GOFAST",
        "sort_order": 2,
        "is_primary": false
      },
      {
        "image_url": "d7c9bc12-0401-49fe-b79c-2485b3a3b2a8.jpg",
        "alt_text": "XE MÁY TAY GA 50CC DIBAO GOFAST",
        "sort_order": 3,
        "is_primary": false
      },
      {
        "image_url": "9ebd2eff-f475-4bf6-94fa-3987526bc7cf.jpg",
        "alt_text": "XE MÁY TAY GA 50CC DIBAO GOFAST",
        "sort_order": 4,
        "is_primary": false
      }
    ],
    "variants": [
      {
        "sku": "xe-máy-tay-ga-50cc-dibao-gofast-default",
        "color": "",
        "size": "",
        "stock_quantity": 20
      }
    ]
  },
  {
    "category_slug": "xe-may-dien",
    "product": {
      "name": "XE MÁY ĐIỆN CÓ BÀN ĐẠP DIBAO AMY",
      "slug": "xe-máy-điện-có-bàn-đạp-dibao-amy",
      "description": "Tốc độ: 35 km/h | Công suất: 1000 W | ắc quy 48v (4x12v) 22ah\n6 tốc độ 30 - 35km/h\n7 quãng đường đi/lần sạc 70km - 90km (tùy theo tốc độ và tải trọng)\n8 lốp xe lốp không săm 2",
      "price": 1639000018890000.0,
      "discount_price": null,
      "stock_quantity": 40,
      "rating": 0,
      "review_count": 0,
      "is_featured": false,
      "is_active": true
    },
    "images": [
      {
        "image_url": "51e655c1-f03d-4690-bc77-f9bdd068d122.jpg",
        "alt_text": "XE MÁY ĐIỆN CÓ BÀN ĐẠP DIBAO AMY",
        "sort_order": 0,
        "is_primary": true
      },
      {
        "image_url": "2eb632e6-3b4d-49a0-b345-154567efedda.jpg",
        "alt_text": "XE MÁY ĐIỆN CÓ BÀN ĐẠP DIBAO AMY",
        "sort_order": 1,
        "is_primary": false
      },
      {
        "image_url": "658fc304-d82f-4dff-badc-cbbe23320f9e.jpg",
        "alt_text": "XE MÁY ĐIỆN CÓ BÀN ĐẠP DIBAO AMY",
        "sort_order": 2,
        "is_primary": false
      },
      {
        "image_url": "4e7cd40d-4f49-4efe-b892-e23d5f77dbcf.jpg",
        "alt_text": "XE MÁY ĐIỆN CÓ BÀN ĐẠP DIBAO AMY",
        "sort_order": 3,
        "is_primary": false
      },
      {
        "image_url": "f57abd51-da4f-4a01-ac4b-f85cb7e9c5c6.jpg",
        "alt_text": "XE MÁY ĐIỆN CÓ BÀN ĐẠP DIBAO AMY",
        "sort_order": 4,
        "is_primary": false
      }
    ],
    "variants": [
      {
        "sku": "xe-máy-điện-có-bàn-đạp-dibao-amy-default",
        "color": "",
        "size": "",
        "stock_quantity": 20
      }
    ]
  },
  {
    "category_slug": "xe-may-dien",
    "product": {
      "name": "XE MÁY ĐIỆN CÓ BÀN ĐẠP DIBAO QUEEN",
      "slug": "xe-máy-điện-có-bàn-đạp-dibao-queen",
      "description": "Tốc độ: 45 km/h | Công suất: 550 W | ắc quy 60v (5x12v) 22ah\n6 tốc độ 40 - 45km/h\n7 quãng đường đi/lần sạc 80km - 90km (tùy theo tốc độ và tải trọng)\n8 lốp xe lốp không săm 3",
      "price": 1299000013990000.0,
      "discount_price": null,
      "stock_quantity": 40,
      "rating": 0,
      "review_count": 0,
      "is_featured": false,
      "is_active": true
    },
    "images": [
      {
        "image_url": "26441a46-a6a8-4664-8f13-8aabeb90cd73.jpg",
        "alt_text": "XE MÁY ĐIỆN CÓ BÀN ĐẠP DIBAO QUEEN",
        "sort_order": 0,
        "is_primary": true
      },
      {
        "image_url": "1932c673-d1a6-471e-8ebe-a6b07886158c.jpg",
        "alt_text": "XE MÁY ĐIỆN CÓ BÀN ĐẠP DIBAO QUEEN",
        "sort_order": 1,
        "is_primary": false
      },
      {
        "image_url": "48ae638a-21eb-45dd-9320-b16adf2654f9.jpg",
        "alt_text": "XE MÁY ĐIỆN CÓ BÀN ĐẠP DIBAO QUEEN",
        "sort_order": 2,
        "is_primary": false
      },
      {
        "image_url": "f8d71536-9c31-4d9e-9a75-1a8b661094de.jpg",
        "alt_text": "XE MÁY ĐIỆN CÓ BÀN ĐẠP DIBAO QUEEN",
        "sort_order": 3,
        "is_primary": false
      },
      {
        "image_url": "a57cfb0d-e751-4e6b-a422-f7cf669a187b.jpg",
        "alt_text": "XE MÁY ĐIỆN CÓ BÀN ĐẠP DIBAO QUEEN",
        "sort_order": 4,
        "is_primary": false
      }
    ],
    "variants": [
      {
        "sku": "xe-máy-điện-có-bàn-đạp-dibao-queen-default",
        "color": "",
        "size": "",
        "stock_quantity": 20
      }
    ]
  },
  {
    "category_slug": "xe-may-dien",
    "product": {
      "name": "XE MÁY ĐIỆN CÓ BÀN ĐẠP DIBAO RYAN",
      "slug": "xe-máy-điện-có-bàn-đạp-dibao-ryan",
      "description": "Tốc độ: 45 km/h | Công suất: 550 W | ắc quy 60v (5x12v) 22ah\ntốc độ 40-45km/h\nquãng đường đi/lần sạc 70km - 90km (tùy theo tốc độ và tải trọng)\nlốp xe lốp không săm 3",
      "price": 1299000013990000.0,
      "discount_price": null,
      "stock_quantity": 40,
      "rating": 0,
      "review_count": 0,
      "is_featured": false,
      "is_active": true
    },
    "images": [
      {
        "image_url": "d4d846f3-3410-42c4-a238-3ef6616d869d.jpg",
        "alt_text": "XE MÁY ĐIỆN CÓ BÀN ĐẠP DIBAO RYAN",
        "sort_order": 0,
        "is_primary": true
      },
      {
        "image_url": "dcabb8b6-509d-49ae-b740-5271e33ff793.jpg",
        "alt_text": "XE MÁY ĐIỆN CÓ BÀN ĐẠP DIBAO RYAN",
        "sort_order": 1,
        "is_primary": false
      },
      {
        "image_url": "09a28215-4936-4eb1-9639-66d62ba4bfbb.jpg",
        "alt_text": "XE MÁY ĐIỆN CÓ BÀN ĐẠP DIBAO RYAN",
        "sort_order": 2,
        "is_primary": false
      },
      {
        "image_url": "09f795a6-e5e9-4c5b-851f-1dea7ed500c2.jpg",
        "alt_text": "XE MÁY ĐIỆN CÓ BÀN ĐẠP DIBAO RYAN",
        "sort_order": 3,
        "is_primary": false
      },
      {
        "image_url": "1fe3da5d-89b9-41c2-815e-d7886b583a47.jpg",
        "alt_text": "XE MÁY ĐIỆN CÓ BÀN ĐẠP DIBAO RYAN",
        "sort_order": 4,
        "is_primary": false
      }
    ],
    "variants": [
      {
        "sku": "xe-máy-điện-có-bàn-đạp-dibao-ryan-default",
        "color": "",
        "size": "",
        "stock_quantity": 20
      }
    ]
  },
  {
    "category_slug": "xe-may-dien",
    "product": {
      "name": "XE MÁY ĐIỆN DIBAO GOGO CROSS G",
      "slug": "xe-máy-điện-dibao-gogo-cross-g",
      "description": "Tốc độ: 50 km/h | Công suất: 350 W | ắc quy 60v (5x12v) 22ah\ntốc độ tối đa 40-50km/h\nquãng đường đi/lần sạc 60-90km (tùy thuộc vào tốc độ di chuyển và tải trọng)\nlốp xe lốp không săm 90/90-10\nkiểu phanh phanh đĩa trước",
      "price": 1299000013990000.0,
      "discount_price": null,
      "stock_quantity": 40,
      "rating": 0,
      "review_count": 0,
      "is_featured": false,
      "is_active": true
    },
    "images": [
      {
        "image_url": "61988e42-f179-441f-b272-e28ec23838b4.jpg",
        "alt_text": "XE MÁY ĐIỆN DIBAO GOGO CROSS G",
        "sort_order": 0,
        "is_primary": true
      },
      {
        "image_url": "a32a3e26-9628-4f37-beca-2287fe4e702a.jpg",
        "alt_text": "XE MÁY ĐIỆN DIBAO GOGO CROSS G",
        "sort_order": 1,
        "is_primary": false
      },
      {
        "image_url": "cb5b34db-ac3b-4c9a-aa77-191fe14f3175.jpg",
        "alt_text": "XE MÁY ĐIỆN DIBAO GOGO CROSS G",
        "sort_order": 2,
        "is_primary": false
      },
      {
        "image_url": "0de71c85-5b5c-4253-b4c7-f1ddf5ad1676.jpg",
        "alt_text": "XE MÁY ĐIỆN DIBAO GOGO CROSS G",
        "sort_order": 3,
        "is_primary": false
      },
      {
        "image_url": "078260f5-ffb2-4306-96ea-b02b94eac5a8.jpg",
        "alt_text": "XE MÁY ĐIỆN DIBAO GOGO CROSS G",
        "sort_order": 4,
        "is_primary": false
      }
    ],
    "variants": [
      {
        "sku": "xe-máy-điện-dibao-gogo-cross-g-default",
        "color": "",
        "size": "",
        "stock_quantity": 20
      }
    ]
  },
  {
    "category_slug": "xe-may-dien",
    "product": {
      "name": "XE MÁY ĐIỆN DIBAO PANSY DIO + 2025",
      "slug": "xe-máy-điện-dibao-pansy-dio-2025",
      "description": "Tốc độ: 50 km/h | Công suất: 350 W | ắc quy 60v (5x12v) 22ah\ntốc độ 45-50km/h\nquãng đường đi/lần sạc 60km - 90km (tùy theo tốc độ và tải trọng)\nlốp xe lốp không săm 90/90-10\nkiểu phanh phanh đĩa trước",
      "price": 1299000013990000.0,
      "discount_price": null,
      "stock_quantity": 40,
      "rating": 0,
      "review_count": 0,
      "is_featured": false,
      "is_active": true
    },
    "images": [
      {
        "image_url": "14c63264-14cb-48f4-8844-b458d9c0cf73.jpg",
        "alt_text": "XE MÁY ĐIỆN DIBAO PANSY DIO + 2025",
        "sort_order": 0,
        "is_primary": true
      },
      {
        "image_url": "0efd8aab-06ce-49b4-8391-c2d555ab1029.jpg",
        "alt_text": "XE MÁY ĐIỆN DIBAO PANSY DIO + 2025",
        "sort_order": 1,
        "is_primary": false
      },
      {
        "image_url": "bd7af6a0-9ad6-4ee1-bb25-76e81336ac9c.jpg",
        "alt_text": "XE MÁY ĐIỆN DIBAO PANSY DIO + 2025",
        "sort_order": 2,
        "is_primary": false
      },
      {
        "image_url": "cd969e92-f441-4b61-89d8-ea57fe26f875.jpg",
        "alt_text": "XE MÁY ĐIỆN DIBAO PANSY DIO + 2025",
        "sort_order": 3,
        "is_primary": false
      },
      {
        "image_url": "c8e6202e-af5e-454f-a0fe-5c2f51954811.jpg",
        "alt_text": "XE MÁY ĐIỆN DIBAO PANSY DIO + 2025",
        "sort_order": 4,
        "is_primary": false
      }
    ],
    "variants": [
      {
        "sku": "xe-máy-điện-dibao-pansy-dio-2025-default",
        "color": "",
        "size": "",
        "stock_quantity": 20
      }
    ]
  },
  {
    "category_slug": "xe-may-dien",
    "product": {
      "name": "XE MÁY ĐIỆN DIBAO TESLA E",
      "slug": "xe-máy-điện-dibao-tesla-e",
      "description": "Tốc độ: 45 km/h | Công suất: 1550 W",
      "price": 1299000013990000.0,
      "discount_price": null,
      "stock_quantity": 40,
      "rating": 0,
      "review_count": 0,
      "is_featured": false,
      "is_active": true
    },
    "images": [
      {
        "image_url": "fe6956de-ce66-496c-a22d-960bf9d6553b.jpg",
        "alt_text": "XE MÁY ĐIỆN DIBAO TESLA E",
        "sort_order": 0,
        "is_primary": true
      },
      {
        "image_url": "44f0aab0-8bb3-467c-953a-6a84a9d82c50.jpg",
        "alt_text": "XE MÁY ĐIỆN DIBAO TESLA E",
        "sort_order": 1,
        "is_primary": false
      },
      {
        "image_url": "18393216-d3ce-4f49-bf3b-dedff4e5cb3d.jpg",
        "alt_text": "XE MÁY ĐIỆN DIBAO TESLA E",
        "sort_order": 2,
        "is_primary": false
      },
      {
        "image_url": "d1e08bef-d397-4137-818b-a96d7498699d.jpg",
        "alt_text": "XE MÁY ĐIỆN DIBAO TESLA E",
        "sort_order": 3,
        "is_primary": false
      },
      {
        "image_url": "0436c9e7-b283-48f5-abbc-59da5429e21c.jpg",
        "alt_text": "XE MÁY ĐIỆN DIBAO TESLA E",
        "sort_order": 4,
        "is_primary": false
      }
    ],
    "variants": [
      {
        "sku": "xe-máy-điện-dibao-tesla-e-default",
        "color": "",
        "size": "",
        "stock_quantity": 20
      }
    ]
  },
  {
    "category_slug": "xe-may-dien",
    "product": {
      "name": "XE MÁY ĐIỆN CÓ BÀN ĐẠP DIBAO ELLA",
      "slug": "xe-máy-điện-có-bàn-đạp-dibao-ella",
      "description": "Tốc độ: 45 km/h | Công suất: 400 W | ắc quy 60v (5x12v) 22ah\n7 tốc độ 40 - 45km/h\n8 quãng đường đi/lần sạc 70km - 90km (tùy theo tốc độ và tải trọng)\n9 lốp xe lốp không săm 3",
      "price": 1299000013990000.0,
      "discount_price": null,
      "stock_quantity": 40,
      "rating": 0,
      "review_count": 0,
      "is_featured": false,
      "is_active": true
    },
    "images": [
      {
        "image_url": "f4ed9ffb-1fef-44dd-a7b7-af4a9d2cfb75.jpg",
        "alt_text": "XE MÁY ĐIỆN CÓ BÀN ĐẠP DIBAO ELLA",
        "sort_order": 0,
        "is_primary": true
      },
      {
        "image_url": "b5d27db2-009d-440f-a72a-8e9aec4f43c9.jpg",
        "alt_text": "XE MÁY ĐIỆN CÓ BÀN ĐẠP DIBAO ELLA",
        "sort_order": 1,
        "is_primary": false
      },
      {
        "image_url": "96f26bf7-f6da-4f65-8662-11af8da5b921.jpg",
        "alt_text": "XE MÁY ĐIỆN CÓ BÀN ĐẠP DIBAO ELLA",
        "sort_order": 2,
        "is_primary": false
      },
      {
        "image_url": "3361f867-9839-4a71-bac6-677aabdd33ab.jpg",
        "alt_text": "XE MÁY ĐIỆN CÓ BÀN ĐẠP DIBAO ELLA",
        "sort_order": 3,
        "is_primary": false
      },
      {
        "image_url": "9c0124c1-4b17-441d-b068-b5e4d24acd87.jpg",
        "alt_text": "XE MÁY ĐIỆN CÓ BÀN ĐẠP DIBAO ELLA",
        "sort_order": 4,
        "is_primary": false
      }
    ],
    "variants": [
      {
        "sku": "xe-máy-điện-có-bàn-đạp-dibao-ella-default",
        "color": "",
        "size": "",
        "stock_quantity": 20
      }
    ]
  },
  {
    "category_slug": "xe-may-dien",
    "product": {
      "name": "Xe máy điện có bàn đạp DIBAO S-ONE",
      "slug": "xe-máy-điện-có-bàn-đạp-dibao-s-one",
      "description": "Tốc độ: 45 km/h | Công suất: 550 W | ắc quy 60v (5x12v) 22ah\n6 tốc độ 40-45km/h\n7 quãng đường đi/lần sạc 70km - 90km (tùy theo tốc độ và tải trọng)\n8 lốp xe lốp không săm 3",
      "price": 1299000013990000.0,
      "discount_price": null,
      "stock_quantity": 40,
      "rating": 0,
      "review_count": 0,
      "is_featured": false,
      "is_active": true
    },
    "images": [
      {
        "image_url": "bc3442ed-bb15-466a-8b99-6e25a251df87.jpg",
        "alt_text": "Xe máy điện có bàn đạp DIBAO S-ONE",
        "sort_order": 0,
        "is_primary": true
      },
      {
        "image_url": "61647cf9-c5e1-4970-ab64-059741fdcd34.jpg",
        "alt_text": "Xe máy điện có bàn đạp DIBAO S-ONE",
        "sort_order": 1,
        "is_primary": false
      },
      {
        "image_url": "ad9ca9b2-c30d-4aba-89f8-806ee09d1b9d.jpg",
        "alt_text": "Xe máy điện có bàn đạp DIBAO S-ONE",
        "sort_order": 2,
        "is_primary": false
      },
      {
        "image_url": "e77ac2c0-6f3a-468f-9738-17dc84b2882d.jpg",
        "alt_text": "Xe máy điện có bàn đạp DIBAO S-ONE",
        "sort_order": 3,
        "is_primary": false
      },
      {
        "image_url": "9acf38b0-75fe-45a7-b389-51a4166170fd.jpg",
        "alt_text": "Xe máy điện có bàn đạp DIBAO S-ONE",
        "sort_order": 4,
        "is_primary": false
      }
    ],
    "variants": [
      {
        "sku": "xe-máy-điện-có-bàn-đạp-dibao-s-one-default",
        "color": "",
        "size": "",
        "stock_quantity": 20
      }
    ]
  },
  {
    "category_slug": "xe-may-dien",
    "product": {
      "name": "XE MÁY ĐIỆN DIBAO TESLA DIO E",
      "slug": "xe-máy-điện-dibao-tesla-dio-e",
      "description": "Tốc độ: 55 km/h | Công suất: 350 W | ắc quy 60v (5x12v) 22ah\n6 tôc độ 45-55km/h\n7 quãng đường đi/lần xạc 60km -90km (tùy theo tốc độ và tải trọng)\n8 lốp xe lốp không săm 90/90-10\n9 kiểu phanh phanh đĩa trước",
      "price": 1299000013990000.0,
      "discount_price": null,
      "stock_quantity": 40,
      "rating": 0,
      "review_count": 0,
      "is_featured": false,
      "is_active": true
    },
    "images": [
      {
        "image_url": "7d4a3184-a046-4aad-865b-719d2240d8fb.jpg",
        "alt_text": "XE MÁY ĐIỆN DIBAO TESLA DIO E",
        "sort_order": 0,
        "is_primary": true
      },
      {
        "image_url": "98adc676-9104-4a97-9f1c-89b387a6e6b9.jpg",
        "alt_text": "XE MÁY ĐIỆN DIBAO TESLA DIO E",
        "sort_order": 1,
        "is_primary": false
      },
      {
        "image_url": "3ee35ee8-db1b-4470-b5cb-94da2b52597e.jpg",
        "alt_text": "XE MÁY ĐIỆN DIBAO TESLA DIO E",
        "sort_order": 2,
        "is_primary": false
      },
      {
        "image_url": "18227722-62f8-4c67-82a3-4a164950cea6.jpg",
        "alt_text": "XE MÁY ĐIỆN DIBAO TESLA DIO E",
        "sort_order": 3,
        "is_primary": false
      },
      {
        "image_url": "75dd8282-1cae-403f-91ce-591449aea52e.jpg",
        "alt_text": "XE MÁY ĐIỆN DIBAO TESLA DIO E",
        "sort_order": 4,
        "is_primary": false
      }
    ],
    "variants": [
      {
        "sku": "xe-máy-điện-dibao-tesla-dio-e-default",
        "color": "",
        "size": "",
        "stock_quantity": 20
      }
    ]
  },
  {
    "category_slug": "xe-may-dien",
    "product": {
      "name": "XE MÁY ĐIỆN DIBAO LS007",
      "slug": "xe-máy-điện-dibao-ls007",
      "description": "Tốc độ: 54 km/h | Công suất: 800 W | ắc quy 72v (5x12v) 22ah\n5 tốc độ 45 - 54km/h\n6 quãng đường đi/lần sạc 60km -100km (tùy theo tốc độ và tải trọng)\n7 lốp xe lốp không săm 90/90-14\n8 kiểu phanh phanh đĩa trước",
      "price": 1299000013990000.0,
      "discount_price": null,
      "stock_quantity": 40,
      "rating": 0,
      "review_count": 0,
      "is_featured": false,
      "is_active": true
    },
    "images": [
      {
        "image_url": "4943f74b-af49-42ea-a7ff-9b7f45cdca35.jpg",
        "alt_text": "XE MÁY ĐIỆN DIBAO LS007",
        "sort_order": 0,
        "is_primary": true
      },
      {
        "image_url": "f7c995a6-a574-425b-a583-ad2f1dce328e.jpg",
        "alt_text": "XE MÁY ĐIỆN DIBAO LS007",
        "sort_order": 1,
        "is_primary": false
      },
      {
        "image_url": "b181f473-7d2c-4110-be27-ee6257cec7e3.jpg",
        "alt_text": "XE MÁY ĐIỆN DIBAO LS007",
        "sort_order": 2,
        "is_primary": false
      },
      {
        "image_url": "8df86dd8-6f91-4001-b92a-e7602bd44ddd.jpg",
        "alt_text": "XE MÁY ĐIỆN DIBAO LS007",
        "sort_order": 3,
        "is_primary": false
      },
      {
        "image_url": "6cdc3675-32f3-4b16-81fc-96a347c95337.jpg",
        "alt_text": "XE MÁY ĐIỆN DIBAO LS007",
        "sort_order": 4,
        "is_primary": false
      }
    ],
    "variants": [
      {
        "sku": "xe-máy-điện-dibao-ls007-default",
        "color": "",
        "size": "",
        "stock_quantity": 20
      }
    ]
  },
  {
    "category_slug": "xe-may-dien",
    "product": {
      "name": "Xe máy điện DIBAO GOGO CROWN",
      "slug": "xe-máy-điện-dibao-gogo-crown",
      "description": "Tốc độ: 54 km/h | Công suất: 600 W | ắc quy 60v (5x12v) 22ah\n6 tôc độ 45-54km/h\n7 quãng đường đi/lần xạc 60km -80km (tùy theo tốc độ và tải trọng)\n8 lốp xe lốp không săm 90/90-10\n9 kiểu phanh phanh đĩa trước",
      "price": 1299000013990000.0,
      "discount_price": null,
      "stock_quantity": 40,
      "rating": 0,
      "review_count": 0,
      "is_featured": false,
      "is_active": true
    },
    "images": [
      {
        "image_url": "bd865ae7-c892-4a69-80b0-03829fac1768.jpg",
        "alt_text": "Xe máy điện DIBAO GOGO CROWN",
        "sort_order": 0,
        "is_primary": true
      },
      {
        "image_url": "854fe6af-89ac-4323-bc6a-ba9c1585b9bb.jpg",
        "alt_text": "Xe máy điện DIBAO GOGO CROWN",
        "sort_order": 1,
        "is_primary": false
      },
      {
        "image_url": "4ca97ea7-0f16-4cd9-b46d-ddf923b774ff.jpg",
        "alt_text": "Xe máy điện DIBAO GOGO CROWN",
        "sort_order": 2,
        "is_primary": false
      },
      {
        "image_url": "b703adfb-f446-4373-94e5-f9035ffb46ee.jpg",
        "alt_text": "Xe máy điện DIBAO GOGO CROWN",
        "sort_order": 3,
        "is_primary": false
      },
      {
        "image_url": "f8a9aba1-3b22-469c-a122-62990b83536f.jpg",
        "alt_text": "Xe máy điện DIBAO GOGO CROWN",
        "sort_order": 4,
        "is_primary": false
      }
    ],
    "variants": [
      {
        "sku": "xe-máy-điện-dibao-gogo-crown-default",
        "color": "",
        "size": "",
        "stock_quantity": 20
      }
    ]
  },
  {
    "category_slug": "xe-may-dien",
    "product": {
      "name": "Xe máy điện DIBAO KEVA",
      "slug": "xe-máy-điện-dibao-keva",
      "description": "Tốc độ: 45 km/h | Công suất: 400 W | ắc quy 60v (5x12v) 22ah\n5 tốc độ 40-45km/h\n6 quãng đường đi/lần sạc 70km - 90km (tùy theo tốc độ và tải trọng)\n7 lốp xe lốp không săm 3",
      "price": 1299000013990000.0,
      "discount_price": null,
      "stock_quantity": 40,
      "rating": 0,
      "review_count": 0,
      "is_featured": false,
      "is_active": true
    },
    "images": [
      {
        "image_url": "184e660e-dc65-43c6-aead-72196ae1376b.jpg",
        "alt_text": "Xe máy điện DIBAO KEVA",
        "sort_order": 0,
        "is_primary": true
      },
      {
        "image_url": "ca5905dd-ddeb-4014-8ec8-1fb6d262c0ae.jpg",
        "alt_text": "Xe máy điện DIBAO KEVA",
        "sort_order": 1,
        "is_primary": false
      },
      {
        "image_url": "a928aeda-a782-4ee1-a224-bc63a5b7a95b.jpg",
        "alt_text": "Xe máy điện DIBAO KEVA",
        "sort_order": 2,
        "is_primary": false
      },
      {
        "image_url": "46c22409-2067-43d0-b9e4-cc456d79204d.jpg",
        "alt_text": "Xe máy điện DIBAO KEVA",
        "sort_order": 3,
        "is_primary": false
      },
      {
        "image_url": "dc2cca58-6411-4609-970b-7b7be322a516.jpg",
        "alt_text": "Xe máy điện DIBAO KEVA",
        "sort_order": 4,
        "is_primary": false
      }
    ],
    "variants": [
      {
        "sku": "xe-máy-điện-dibao-keva-default",
        "color": "",
        "size": "",
        "stock_quantity": 20
      }
    ]
  },
  {
    "category_slug": "xe-may-dien",
    "product": {
      "name": "XE MÁY ĐIỆN DIBAO MXS",
      "slug": "xe-máy-điện-dibao-mxs",
      "description": "Tốc độ: 45 km/h | Công suất: 400 W | ắc quy 60v (5x12v) 23ah\n5 tôc độ 40-45km/h\n6 quãng đường đi/lần xạc 70km -80km (tùy theo tốc độ và tải trọng)\n7 lốp xe lốp không săm 90/80-12\n8 kiểu phanh phanh đĩa trước",
      "price": 1299000013990000.0,
      "discount_price": null,
      "stock_quantity": 40,
      "rating": 0,
      "review_count": 0,
      "is_featured": false,
      "is_active": true
    },
    "images": [
      {
        "image_url": "d0f95705-64f4-4d63-b09f-a763dbf3cf25.jpg",
        "alt_text": "XE MÁY ĐIỆN DIBAO MXS",
        "sort_order": 0,
        "is_primary": true
      },
      {
        "image_url": "b0746806-ab01-47c1-8b18-2aba2863e85e.jpg",
        "alt_text": "XE MÁY ĐIỆN DIBAO MXS",
        "sort_order": 1,
        "is_primary": false
      },
      {
        "image_url": "ce0577f7-1a0b-4af3-9e4f-0a3fecf52724.jpg",
        "alt_text": "XE MÁY ĐIỆN DIBAO MXS",
        "sort_order": 2,
        "is_primary": false
      },
      {
        "image_url": "d75b5a89-045f-4bde-85c5-bbd83244400d.jpg",
        "alt_text": "XE MÁY ĐIỆN DIBAO MXS",
        "sort_order": 3,
        "is_primary": false
      },
      {
        "image_url": "bf842815-3331-4d94-883c-43edfd25ba4d.jpg",
        "alt_text": "XE MÁY ĐIỆN DIBAO MXS",
        "sort_order": 4,
        "is_primary": false
      }
    ],
    "variants": [
      {
        "sku": "xe-máy-điện-dibao-mxs-default",
        "color": "",
        "size": "",
        "stock_quantity": 20
      }
    ]
  },
  {
    "category_slug": "xe-may-dien",
    "product": {
      "name": "XE MÁY ĐIỆN DIBAO ROSA",
      "slug": "xe-máy-điện-dibao-rosa",
      "description": "Tốc độ: 45 km/h | Công suất: 400 W | ắc quy 60v (5x12v) 23ah\n6 tốc độ 40 - 45km/h\n7 quãng đường đi/lần sạc 80km - 90km (tùy theo tốc độ và tải trọng)\n8 lốp xe lốp không săm 3",
      "price": 1299000013990000.0,
      "discount_price": null,
      "stock_quantity": 40,
      "rating": 0,
      "review_count": 0,
      "is_featured": false,
      "is_active": true
    },
    "images": [
      {
        "image_url": "d4c0fefb-7f55-47f5-859e-82290fac7c9b.jpg",
        "alt_text": "XE MÁY ĐIỆN DIBAO ROSA",
        "sort_order": 0,
        "is_primary": true
      },
      {
        "image_url": "956e831b-5989-4851-9bcf-d9e763abaffb.jpg",
        "alt_text": "XE MÁY ĐIỆN DIBAO ROSA",
        "sort_order": 1,
        "is_primary": false
      },
      {
        "image_url": "fbc678f0-055c-41e2-af29-672e5c96afbe.jpg",
        "alt_text": "XE MÁY ĐIỆN DIBAO ROSA",
        "sort_order": 2,
        "is_primary": false
      },
      {
        "image_url": "8cf1ef2d-3e4c-41c5-869f-0d0614a43c50.jpg",
        "alt_text": "XE MÁY ĐIỆN DIBAO ROSA",
        "sort_order": 3,
        "is_primary": false
      },
      {
        "image_url": "c915d0ec-5431-40bf-bb2a-58917329f0e4.jpg",
        "alt_text": "XE MÁY ĐIỆN DIBAO ROSA",
        "sort_order": 4,
        "is_primary": false
      }
    ],
    "variants": [
      {
        "sku": "xe-máy-điện-dibao-rosa-default",
        "color": "",
        "size": "",
        "stock_quantity": 20
      }
    ]
  },
  {
    "category_slug": "xe-may-dien",
    "product": {
      "name": "XE MÁY ĐIỆN DIBAO TESLA CHIC Q",
      "slug": "xe-máy-điện-dibao-tesla-chic-q",
      "description": "Tốc độ: 50 km/h | Công suất: 500 W | ắc quy 60v (5x12v) 22ah\n8\ntốc độ tối đa\n45 - 50km/h\n9\nquãng đường đi/lần sạc\n60 - 80km (tùy thuộc vào tốc độ di chuyển và tải trọng)\n10\nlốp xe\nlốp không săm 3",
      "price": 1299000013990000.0,
      "discount_price": null,
      "stock_quantity": 40,
      "rating": 0,
      "review_count": 0,
      "is_featured": false,
      "is_active": true
    },
    "images": [
      {
        "image_url": "31e9648c-97c3-40b2-811a-0a2fd27d6866.jpg",
        "alt_text": "XE MÁY ĐIỆN DIBAO TESLA CHIC Q",
        "sort_order": 0,
        "is_primary": true
      },
      {
        "image_url": "c304a5df-3fb2-4d8e-b8f7-26c036286f9b.jpg",
        "alt_text": "XE MÁY ĐIỆN DIBAO TESLA CHIC Q",
        "sort_order": 1,
        "is_primary": false
      },
      {
        "image_url": "8d5cd240-9035-40ee-ac96-da357f602dc8.jpg",
        "alt_text": "XE MÁY ĐIỆN DIBAO TESLA CHIC Q",
        "sort_order": 2,
        "is_primary": false
      },
      {
        "image_url": "a34b884d-050f-43a0-81cb-5a12a8179640.jpg",
        "alt_text": "XE MÁY ĐIỆN DIBAO TESLA CHIC Q",
        "sort_order": 3,
        "is_primary": false
      },
      {
        "image_url": "7b0d6171-8803-4fd0-98c2-2d4ed61f6fcb.jpg",
        "alt_text": "XE MÁY ĐIỆN DIBAO TESLA CHIC Q",
        "sort_order": 4,
        "is_primary": false
      }
    ],
    "variants": [
      {
        "sku": "xe-máy-điện-dibao-tesla-chic-q-default",
        "color": "",
        "size": "",
        "stock_quantity": 20
      }
    ]
  },
  {
    "category_slug": "xe-may-dien",
    "product": {
      "name": "XE MÁY ĐIỆN DIBAO GOGO MOON",
      "slug": "xe-máy-điện-dibao-gogo-moon",
      "description": "Tốc độ: 50 km/h | Công suất: 500 W | ắc quy 60v (5x12v) 22ah\n8\ntốc độ tối đa\n45-50km/h\n9\nquãng đường đi/lần sạc\n60-80km (tùy thuộc vào tốc độ di chuyển và tải trọng)\n10\nlốp xe\nlốp không săm 3",
      "price": 1299000013990000.0,
      "discount_price": null,
      "stock_quantity": 40,
      "rating": 0,
      "review_count": 0,
      "is_featured": false,
      "is_active": true
    },
    "images": [
      {
        "image_url": "fb9b99c4-d213-4073-b848-4627142072f6.jpg",
        "alt_text": "XE MÁY ĐIỆN DIBAO GOGO MOON",
        "sort_order": 0,
        "is_primary": true
      },
      {
        "image_url": "6fc456e5-9b50-4282-afd5-2106a514f81e.jpg",
        "alt_text": "XE MÁY ĐIỆN DIBAO GOGO MOON",
        "sort_order": 1,
        "is_primary": false
      },
      {
        "image_url": "3c6efbb3-6cc5-478b-b0a7-e10891636cca.jpg",
        "alt_text": "XE MÁY ĐIỆN DIBAO GOGO MOON",
        "sort_order": 2,
        "is_primary": false
      },
      {
        "image_url": "bb134c33-21c7-4a3f-a05b-7b84ffe8f3de.jpg",
        "alt_text": "XE MÁY ĐIỆN DIBAO GOGO MOON",
        "sort_order": 3,
        "is_primary": false
      },
      {
        "image_url": "df62f53f-9ff8-4011-a757-7d130243e3af.jpg",
        "alt_text": "XE MÁY ĐIỆN DIBAO GOGO MOON",
        "sort_order": 4,
        "is_primary": false
      }
    ],
    "variants": [
      {
        "sku": "xe-máy-điện-dibao-gogo-moon-default",
        "color": "",
        "size": "",
        "stock_quantity": 20
      }
    ]
  },
  {
    "category_slug": "xe-may-dien",
    "product": {
      "name": "XE MÁY ĐIỆN DIBAO TESLA CHIC",
      "slug": "xe-máy-điện-dibao-tesla-chic",
      "description": "Tốc độ: 50 km/h | Công suất: 500 W | ắc quy 60v (5x12v) 23ah\n7\ntốc độ tối đa\n45-50km/h\n8\nquãng đường đi/lần sạc\n60-80km (tùy thuộc vào tốc độ di chuyển và tải trọng)\n9\nlốp xe\nlốp không săm 3",
      "price": 1299000013990000.0,
      "discount_price": null,
      "stock_quantity": 40,
      "rating": 0,
      "review_count": 0,
      "is_featured": false,
      "is_active": true
    },
    "images": [
      {
        "image_url": "b7a4ff23-f657-4e14-b281-b3f08bb1e9fb.jpg",
        "alt_text": "XE MÁY ĐIỆN DIBAO TESLA CHIC",
        "sort_order": 0,
        "is_primary": true
      },
      {
        "image_url": "83040cc2-92fe-4bb9-ab29-6f582cdc1f04.jpg",
        "alt_text": "XE MÁY ĐIỆN DIBAO TESLA CHIC",
        "sort_order": 1,
        "is_primary": false
      },
      {
        "image_url": "58d47789-023a-407b-9a81-5bded6a0cd8f.jpg",
        "alt_text": "XE MÁY ĐIỆN DIBAO TESLA CHIC",
        "sort_order": 2,
        "is_primary": false
      },
      {
        "image_url": "622df9e0-df50-472b-904c-5f78c718604b.jpg",
        "alt_text": "XE MÁY ĐIỆN DIBAO TESLA CHIC",
        "sort_order": 3,
        "is_primary": false
      },
      {
        "image_url": "42bd8149-0f48-478f-835c-a3bfbf166861.jpg",
        "alt_text": "XE MÁY ĐIỆN DIBAO TESLA CHIC",
        "sort_order": 4,
        "is_primary": false
      }
    ],
    "variants": [
      {
        "sku": "xe-máy-điện-dibao-tesla-chic-default",
        "color": "",
        "size": "",
        "stock_quantity": 20
      }
    ]
  },
  {
    "category_slug": "xe-may-dien",
    "product": {
      "name": "SSL handshake failed Error code 525",
      "slug": "ssl-handshake-failed-error-code-525",
      "description": "",
      "price": 0,
      "discount_price": null,
      "stock_quantity": 40,
      "rating": 0,
      "review_count": 0,
      "is_featured": false,
      "is_active": true
    },
    "images": [],
    "variants": [
      {
        "sku": "ssl-handshake-failed-error-code-525-default",
        "color": "",
        "size": "",
        "stock_quantity": 20
      }
    ]
  },
  {
    "category_slug": "xe-may-dien",
    "product": {
      "name": "XE MÁY ĐIỆN DIBAO PANSY SQ2",
      "slug": "xe-máy-điện-dibao-pansy-sq2",
      "description": "Tốc độ: 50 km/h | Công suất: 450 W | ắc quy 60v (5x12v) 23ah\n7\ntôc độ tối đa\n45-50km/h\n8\nquãng đường đi/lần xạc\n60-90km (tùy thuộc vào tốc độ di chuyển và tải trọng)\n9\nlốp xe\nlốp không săm 90/90-10\n10\nkiểu phanh\nphanh đĩa trước",
      "price": 1299000013990000.0,
      "discount_price": null,
      "stock_quantity": 40,
      "rating": 0,
      "review_count": 0,
      "is_featured": false,
      "is_active": true
    },
    "images": [
      {
        "image_url": "79a05f71-b430-4900-b683-4c709654124d.jpg",
        "alt_text": "XE MÁY ĐIỆN DIBAO PANSY SQ2",
        "sort_order": 0,
        "is_primary": true
      },
      {
        "image_url": "a7d622d3-4101-4613-ba51-91328b4f29a0.jpg",
        "alt_text": "XE MÁY ĐIỆN DIBAO PANSY SQ2",
        "sort_order": 1,
        "is_primary": false
      },
      {
        "image_url": "6af973ab-2c77-4237-a732-f4b3f398f315.jpg",
        "alt_text": "XE MÁY ĐIỆN DIBAO PANSY SQ2",
        "sort_order": 2,
        "is_primary": false
      },
      {
        "image_url": "b988f49d-877e-47ee-bffd-5a94f1fb3b54.jpg",
        "alt_text": "XE MÁY ĐIỆN DIBAO PANSY SQ2",
        "sort_order": 3,
        "is_primary": false
      },
      {
        "image_url": "92a947b3-09cd-4af3-be3f-13daf6ee349f.jpg",
        "alt_text": "XE MÁY ĐIỆN DIBAO PANSY SQ2",
        "sort_order": 4,
        "is_primary": false
      }
    ],
    "variants": [
      {
        "sku": "xe-máy-điện-dibao-pansy-sq2-default",
        "color": "",
        "size": "",
        "stock_quantity": 20
      }
    ]
  },
  {
    "category_slug": "xe-may-dien",
    "product": {
      "name": "XE MÁY ĐIỆN DIBAO XMAN-LEO",
      "slug": "xe-máy-điện-dibao-xman-leo",
      "description": "Tốc độ: 55 km/h | Công suất: 450 W | ắc quy 60v (5x12v) 23ah\n7\ntôc độ\n45-55km/h\n8\nquãng đường đi/lần xạc\n60-90km (tùy thuộc vào tốc độ di chuyển và tải trọng)\n9\nlốp xe\nlốp không săm 90/90-10\n10\nkiểu phanh\nphanh đĩa trước",
      "price": 1299000013990000.0,
      "discount_price": null,
      "stock_quantity": 40,
      "rating": 0,
      "review_count": 0,
      "is_featured": false,
      "is_active": true
    },
    "images": [
      {
        "image_url": "9d9d267f-5c9b-4238-98cb-4320c7d8aa0b.jpg",
        "alt_text": "XE MÁY ĐIỆN DIBAO XMAN-LEO",
        "sort_order": 0,
        "is_primary": true
      },
      {
        "image_url": "2c62ff32-2638-4f5c-8233-e5e7eb91ea69.jpg",
        "alt_text": "XE MÁY ĐIỆN DIBAO XMAN-LEO",
        "sort_order": 1,
        "is_primary": false
      },
      {
        "image_url": "cd84522f-38a0-4adc-9285-b0fba09237d6.jpg",
        "alt_text": "XE MÁY ĐIỆN DIBAO XMAN-LEO",
        "sort_order": 2,
        "is_primary": false
      },
      {
        "image_url": "33105fec-a5a3-49d8-b397-3ade6819ab71.jpg",
        "alt_text": "XE MÁY ĐIỆN DIBAO XMAN-LEO",
        "sort_order": 3,
        "is_primary": false
      },
      {
        "image_url": "1358a0bb-2ae7-4a18-bfa0-e1883c599467.jpg",
        "alt_text": "XE MÁY ĐIỆN DIBAO XMAN-LEO",
        "sort_order": 4,
        "is_primary": false
      }
    ],
    "variants": [
      {
        "sku": "xe-máy-điện-dibao-xman-leo-default",
        "color": "",
        "size": "",
        "stock_quantity": 20
      }
    ]
  },
  {
    "category_slug": "xe-may-dien",
    "product": {
      "name": "XE MÁY ĐIỆN DIBAO CREER E",
      "slug": "xe-máy-điện-dibao-creer-e",
      "description": "Tốc độ: 50 km/h | Công suất: 400 W | ắc quy 60v (5x12v) 23ah\n7\ntôc độ tối đa\n40-50km/h\n8\nquãng đường đi/lần xạc\n60-90km (tùy thuộc vào tốc độ di chuyển và tải trọng)\n9\nlốp xe\nlốp không săm 90/90-10\n10\nkiểu phanh\nphanh đĩa trước",
      "price": 1299000013990000.0,
      "discount_price": null,
      "stock_quantity": 40,
      "rating": 0,
      "review_count": 0,
      "is_featured": false,
      "is_active": true
    },
    "images": [
      {
        "image_url": "6c776e80-fb3b-4d28-b237-d546b16066e3.jpg",
        "alt_text": "XE MÁY ĐIỆN DIBAO CREER E",
        "sort_order": 0,
        "is_primary": true
      },
      {
        "image_url": "a67f7b2b-cb0a-4d7c-a2ac-b13150de0df6.jpg",
        "alt_text": "XE MÁY ĐIỆN DIBAO CREER E",
        "sort_order": 1,
        "is_primary": false
      },
      {
        "image_url": "cee643a3-546f-4ad6-9ddd-6931eb5414e6.jpg",
        "alt_text": "XE MÁY ĐIỆN DIBAO CREER E",
        "sort_order": 2,
        "is_primary": false
      },
      {
        "image_url": "380de1d7-3134-4a8c-87cf-0ea8ede7338b.jpg",
        "alt_text": "XE MÁY ĐIỆN DIBAO CREER E",
        "sort_order": 3,
        "is_primary": false
      },
      {
        "image_url": "ac3b3d02-a51a-4e9c-bd04-4fb92f3d175c.jpg",
        "alt_text": "XE MÁY ĐIỆN DIBAO CREER E",
        "sort_order": 4,
        "is_primary": false
      }
    ],
    "variants": [
      {
        "sku": "xe-máy-điện-dibao-creer-e-default",
        "color": "",
        "size": "",
        "stock_quantity": 20
      }
    ]
  },
  {
    "category_slug": "xe-may-dien",
    "product": {
      "name": "XE MÁY ĐIỆN DIBAO GOGO CROSS",
      "slug": "xe-máy-điện-dibao-gogo-cross",
      "description": "Tốc độ: 50 km/h | Công suất: 450 W | ắc quy 60v (5x12v) 23ah\n7\ntôc độ tối đa\n40-50km/h\n8\nquãng đường đi/lần xạc\n60-90km (tùy thuộc vào tốc độ di chuyển và tải trọng)\n9\nlốp xe\nlốp không săm 90/90-10\n10\nkiểu phanh\nphanh đĩa trước",
      "price": 1299000013990000.0,
      "discount_price": null,
      "stock_quantity": 40,
      "rating": 0,
      "review_count": 0,
      "is_featured": false,
      "is_active": true
    },
    "images": [
      {
        "image_url": "8c809e92-76a6-47b7-ad28-b613c3cdffd2.jpg",
        "alt_text": "XE MÁY ĐIỆN DIBAO GOGO CROSS",
        "sort_order": 0,
        "is_primary": true
      },
      {
        "image_url": "6ec7a7ac-1407-4fae-a93b-2e2442098750.jpg",
        "alt_text": "XE MÁY ĐIỆN DIBAO GOGO CROSS",
        "sort_order": 1,
        "is_primary": false
      },
      {
        "image_url": "ac54602a-4c30-4941-a1cf-5453fa87eff4.jpg",
        "alt_text": "XE MÁY ĐIỆN DIBAO GOGO CROSS",
        "sort_order": 2,
        "is_primary": false
      },
      {
        "image_url": "b3727e83-b718-47d0-9591-fb5debeb71c3.jpg",
        "alt_text": "XE MÁY ĐIỆN DIBAO GOGO CROSS",
        "sort_order": 3,
        "is_primary": false
      },
      {
        "image_url": "62647083-5b26-46c4-99cc-53b9e1d3c47f.jpg",
        "alt_text": "XE MÁY ĐIỆN DIBAO GOGO CROSS",
        "sort_order": 4,
        "is_primary": false
      }
    ],
    "variants": [
      {
        "sku": "xe-máy-điện-dibao-gogo-cross-default",
        "color": "",
        "size": "",
        "stock_quantity": 20
      }
    ]
  },
  {
    "category_slug": "xe-may-dien",
    "product": {
      "name": "XE MÁY ĐIỆN DIBAO TESLA SD",
      "slug": "xe-máy-điện-dibao-tesla-sd",
      "description": "Tốc độ: 50 km/h | Công suất: 450 W | ắc quy 60v (5x12v) 23ah\n7\ntôc độ tối đa\n45-50km/h\n8\nquãng đường đi/lần xạc\n60-100km (tùy theo tốc độ và tải trọng)\n9\nlốp xe\nlốp không săm 90/90-10\n10\nkiểu phanh\nphanh đĩa trước",
      "price": 1299000013990000.0,
      "discount_price": null,
      "stock_quantity": 40,
      "rating": 0,
      "review_count": 0,
      "is_featured": false,
      "is_active": true
    },
    "images": [
      {
        "image_url": "f480a0d1-b704-4620-a19c-462d3afbb693.jpg",
        "alt_text": "XE MÁY ĐIỆN DIBAO TESLA SD",
        "sort_order": 0,
        "is_primary": true
      },
      {
        "image_url": "9087c72b-5bef-46cd-a69a-fa42f5fb5572.jpg",
        "alt_text": "XE MÁY ĐIỆN DIBAO TESLA SD",
        "sort_order": 1,
        "is_primary": false
      },
      {
        "image_url": "6dc931da-b73a-47d7-804a-879a6e559308.jpg",
        "alt_text": "XE MÁY ĐIỆN DIBAO TESLA SD",
        "sort_order": 2,
        "is_primary": false
      },
      {
        "image_url": "7715455c-95ae-4a8a-8e72-06219207e824.jpg",
        "alt_text": "XE MÁY ĐIỆN DIBAO TESLA SD",
        "sort_order": 3,
        "is_primary": false
      },
      {
        "image_url": "2f22ad1c-96cb-4a46-ba4d-54d13ea30b46.jpg",
        "alt_text": "XE MÁY ĐIỆN DIBAO TESLA SD",
        "sort_order": 4,
        "is_primary": false
      }
    ],
    "variants": [
      {
        "sku": "xe-máy-điện-dibao-tesla-sd-default",
        "color": "",
        "size": "",
        "stock_quantity": 20
      }
    ]
  },
  {
    "category_slug": "xe-may-dien",
    "product": {
      "name": "XE ĐIỆN DIBAO R1",
      "slug": "xe-điện-dibao-r1",
      "description": "Tốc độ: 50 km/h | Công suất: 500 W | ắc quy 60v (5x12v) 23ah\n7\ntôc độ tối đa\n45-50km/h\n8\nquãng đường đi/lần xạc\n60-90km (tùy thuộc vào tốc độ di chuyển và tải trọng)\n9\nlốp xe\nlốp không săm 90/90-10\n10\nkiểu phanh\nphanh đĩa trước",
      "price": 1299000013990000.0,
      "discount_price": null,
      "stock_quantity": 40,
      "rating": 0,
      "review_count": 0,
      "is_featured": false,
      "is_active": true
    },
    "images": [
      {
        "image_url": "c61068fc-2166-4fa8-9e5a-074d0aec2251.jpg",
        "alt_text": "XE ĐIỆN DIBAO R1",
        "sort_order": 0,
        "is_primary": true
      },
      {
        "image_url": "80dcb4cc-8370-4279-b73f-98414fafda0a.jpg",
        "alt_text": "XE ĐIỆN DIBAO R1",
        "sort_order": 1,
        "is_primary": false
      },
      {
        "image_url": "39837c07-e69c-4bb2-a97b-3dced6e4fb9d.jpg",
        "alt_text": "XE ĐIỆN DIBAO R1",
        "sort_order": 2,
        "is_primary": false
      },
      {
        "image_url": "8ab609d2-29ad-4a58-ac5c-a0339c129faf.jpg",
        "alt_text": "XE ĐIỆN DIBAO R1",
        "sort_order": 3,
        "is_primary": false
      },
      {
        "image_url": "ce6c138a-055e-4907-8b6d-24070d19ef91.jpg",
        "alt_text": "XE ĐIỆN DIBAO R1",
        "sort_order": 4,
        "is_primary": false
      }
    ],
    "variants": [
      {
        "sku": "xe-điện-dibao-r1-default",
        "color": "",
        "size": "",
        "stock_quantity": 20
      }
    ]
  },
  {
    "category_slug": "xe-may-dien",
    "product": {
      "name": "XE ĐIỆN DIBAO GOGO S4",
      "slug": "xe-điện-dibao-gogo-s4",
      "description": "Tốc độ: 50 km/h | Công suất: 450 W | ắc quy 60v (5x12v) 22ah\n7\ntôc độ tối đa\n40-50km/h\n8\nquãng đường đi/lần xạc\n60-90km (tùy thuộc vào tốc độ di chuyển và tải trọng)\n9\nlốp xe\nlốp không săm 3",
      "price": 1299000013990000.0,
      "discount_price": null,
      "stock_quantity": 40,
      "rating": 0,
      "review_count": 0,
      "is_featured": false,
      "is_active": true
    },
    "images": [
      {
        "image_url": "f4bef19e-6001-46d5-b0a4-3c143065cd45.jpg",
        "alt_text": "XE ĐIỆN DIBAO GOGO S4",
        "sort_order": 0,
        "is_primary": true
      },
      {
        "image_url": "db1d9304-3142-442a-bf77-718434c16af2.jpg",
        "alt_text": "XE ĐIỆN DIBAO GOGO S4",
        "sort_order": 1,
        "is_primary": false
      },
      {
        "image_url": "b4459ebd-81e8-4d5d-af22-a98ae5214fe2.jpg",
        "alt_text": "XE ĐIỆN DIBAO GOGO S4",
        "sort_order": 2,
        "is_primary": false
      },
      {
        "image_url": "28138bbb-9e9b-4d42-9aab-f2acc6ed64fc.jpg",
        "alt_text": "XE ĐIỆN DIBAO GOGO S4",
        "sort_order": 3,
        "is_primary": false
      },
      {
        "image_url": "b41cdf3d-a218-4eaa-95cc-76dfc550c8f7.jpg",
        "alt_text": "XE ĐIỆN DIBAO GOGO S4",
        "sort_order": 4,
        "is_primary": false
      }
    ],
    "variants": [
      {
        "sku": "xe-điện-dibao-gogo-s4-default",
        "color": "",
        "size": "",
        "stock_quantity": 20
      }
    ]
  },
  {
    "category_slug": "xe-may-dien",
    "product": {
      "name": "XE ĐIỆN DIBAO JEEK ONE",
      "slug": "xe-điện-dibao-jeek-one",
      "description": "Tốc độ: 50 km/h | Công suất: 500 W | ắc quy 60v (5x12v) 21",
      "price": 1299000013990000.0,
      "discount_price": null,
      "stock_quantity": 40,
      "rating": 0,
      "review_count": 0,
      "is_featured": false,
      "is_active": true
    },
    "images": [
      {
        "image_url": "cb9acb99-b094-4830-a814-616be7e524a1.jpg",
        "alt_text": "XE ĐIỆN DIBAO JEEK ONE",
        "sort_order": 0,
        "is_primary": true
      },
      {
        "image_url": "7ae38a14-0be9-422d-96d9-7e88d5faa983.jpg",
        "alt_text": "XE ĐIỆN DIBAO JEEK ONE",
        "sort_order": 1,
        "is_primary": false
      },
      {
        "image_url": "1f82c48c-b3bf-499b-88c2-57eab7d99f88.jpg",
        "alt_text": "XE ĐIỆN DIBAO JEEK ONE",
        "sort_order": 2,
        "is_primary": false
      },
      {
        "image_url": "4755ec72-ef43-46e9-aff3-a18d8e0fd8b4.jpg",
        "alt_text": "XE ĐIỆN DIBAO JEEK ONE",
        "sort_order": 3,
        "is_primary": false
      },
      {
        "image_url": "fd2d507d-2581-452e-ba27-7ce64820c330.jpg",
        "alt_text": "XE ĐIỆN DIBAO JEEK ONE",
        "sort_order": 4,
        "is_primary": false
      }
    ],
    "variants": [
      {
        "sku": "xe-điện-dibao-jeek-one-default",
        "color": "",
        "size": "",
        "stock_quantity": 20
      }
    ]
  },
  {
    "category_slug": "xe-may-dien",
    "product": {
      "name": "XE MÁY ĐIỆN DIBAO M-ONE",
      "slug": "xe-máy-điện-dibao-m-one",
      "description": "Tốc độ: 40 km/h | Công suất: 980 W | ắc quy 48v (4x12v) 20ah+\n7\ntôc độ tối đa\n35-40km/h\n8\nquãng đường đi/lần xạc\n60-110km (tùy theo vận tốc di chuyển và tải trọng)\n9\nlốp xe\nlốp không săm 3",
      "price": 1299000013990000.0,
      "discount_price": null,
      "stock_quantity": 40,
      "rating": 0,
      "review_count": 0,
      "is_featured": false,
      "is_active": true
    },
    "images": [
      {
        "image_url": "7a868f43-1ad3-45b4-a643-73e12aeafa30.jpg",
        "alt_text": "XE MÁY ĐIỆN DIBAO M-ONE",
        "sort_order": 0,
        "is_primary": true
      },
      {
        "image_url": "141c56c1-d02b-4181-83d7-d121e05201c0.jpg",
        "alt_text": "XE MÁY ĐIỆN DIBAO M-ONE",
        "sort_order": 1,
        "is_primary": false
      },
      {
        "image_url": "6609ff35-3a43-4829-afd7-135b6d22da9f.jpg",
        "alt_text": "XE MÁY ĐIỆN DIBAO M-ONE",
        "sort_order": 2,
        "is_primary": false
      },
      {
        "image_url": "8c3a56a0-4242-4463-942d-a309480f37dc.jpg",
        "alt_text": "XE MÁY ĐIỆN DIBAO M-ONE",
        "sort_order": 3,
        "is_primary": false
      },
      {
        "image_url": "76349c29-4841-4859-b142-09beb678864e.jpg",
        "alt_text": "XE MÁY ĐIỆN DIBAO M-ONE",
        "sort_order": 4,
        "is_primary": false
      }
    ],
    "variants": [
      {
        "sku": "xe-máy-điện-dibao-m-one-default",
        "color": "",
        "size": "",
        "stock_quantity": 20
      }
    ]
  },
  {
    "category_slug": "xe-may-dien",
    "product": {
      "name": "XE ĐIỆN DIBAO BUTTERFLY",
      "slug": "xe-điện-dibao-butterfly",
      "description": "Tốc độ: 50 km/h | Công suất: 500 W | ắc quy 60v (5x12v) 21",
      "price": 1299000013990000.0,
      "discount_price": null,
      "stock_quantity": 40,
      "rating": 0,
      "review_count": 0,
      "is_featured": false,
      "is_active": true
    },
    "images": [
      {
        "image_url": "8585a182-27fd-4ba9-8dff-4ee78f0ebf4a.jpg",
        "alt_text": "XE ĐIỆN DIBAO BUTTERFLY",
        "sort_order": 0,
        "is_primary": true
      },
      {
        "image_url": "11046231-fb29-4b5c-963b-c7f2572fe175.jpg",
        "alt_text": "XE ĐIỆN DIBAO BUTTERFLY",
        "sort_order": 1,
        "is_primary": false
      },
      {
        "image_url": "6ceba0e5-bf23-4a75-9de3-6ee3dd3ff3f5.jpg",
        "alt_text": "XE ĐIỆN DIBAO BUTTERFLY",
        "sort_order": 2,
        "is_primary": false
      },
      {
        "image_url": "b27a568e-40cc-49cd-8ce1-6c9046a6f792.jpg",
        "alt_text": "XE ĐIỆN DIBAO BUTTERFLY",
        "sort_order": 3,
        "is_primary": false
      },
      {
        "image_url": "a56c32ab-d2c2-4e6e-bf45-178a0dc80397.jpg",
        "alt_text": "XE ĐIỆN DIBAO BUTTERFLY",
        "sort_order": 4,
        "is_primary": false
      }
    ],
    "variants": [
      {
        "sku": "xe-điện-dibao-butterfly-default",
        "color": "",
        "size": "",
        "stock_quantity": 20
      }
    ]
  },
  {
    "category_slug": "xe-dap-dien",
    "product": {
      "name": "XE MÁY ĐIỆN DIBAO PANSY S3",
      "slug": "xe-máy-điện-dibao-pansy-s3",
      "description": "Tốc độ: 50 km/h | Công suất: 350 W | ắc quy 60v (5x12v) 22ah\n8\ntôc độ tối đa\n45-50km/h\n9\nquãng đường đi/lần xạc\n60-90km (tùy thuộc vào tốc độ di chuyển và tải trọng)\n10\nlốp xe\nlốp không săm 3",
      "price": 1299000013990000.0,
      "discount_price": null,
      "stock_quantity": 40,
      "rating": 0,
      "review_count": 0,
      "is_featured": false,
      "is_active": true
    },
    "images": [
      {
        "image_url": "f2625c5c-dbb1-41c2-ba44-5b625214f277.jpg",
        "alt_text": "XE MÁY ĐIỆN DIBAO PANSY S3",
        "sort_order": 0,
        "is_primary": true
      },
      {
        "image_url": "aa4d98c6-f673-4c08-9bd9-f9cd31e719eb.jpg",
        "alt_text": "XE MÁY ĐIỆN DIBAO PANSY S3",
        "sort_order": 1,
        "is_primary": false
      },
      {
        "image_url": "779bdff3-f4f6-4b2a-9e5e-a672e1d00038.jpg",
        "alt_text": "XE MÁY ĐIỆN DIBAO PANSY S3",
        "sort_order": 2,
        "is_primary": false
      },
      {
        "image_url": "0777e2bf-7046-499c-84e8-07fe24fb7238.jpg",
        "alt_text": "XE MÁY ĐIỆN DIBAO PANSY S3",
        "sort_order": 3,
        "is_primary": false
      },
      {
        "image_url": "0edff361-f612-4bfe-9556-8f61701530ee.jpg",
        "alt_text": "XE MÁY ĐIỆN DIBAO PANSY S3",
        "sort_order": 4,
        "is_primary": false
      }
    ],
    "variants": [
      {
        "sku": "xe-máy-điện-dibao-pansy-s3-default",
        "color": "",
        "size": "",
        "stock_quantity": 20
      }
    ]
  },
  {
    "category_slug": "xe-dap-dien",
    "product": {
      "name": "XE MÁY ĐIỆN DIBAO PANSY S2 (CÀNG NHÔM)",
      "slug": "xe-máy-điện-dibao-pansy-s2-càng-nhôm",
      "description": "Tốc độ: 50 km/h | Công suất: 450 W | ắc quy 60v (5x12v) 22ah\n7\ntôc độ tối đa\n45-50km/h\n8\nquãng đường đi/lần xạc\n60-100km (tùy theo tốc độ di chuyển và tải trọng)\n9\nlốp xe\nlốp không săm 90/90-10\n10\nkiểu phanh\nphanh đĩa trước",
      "price": 1299000013990000.0,
      "discount_price": null,
      "stock_quantity": 40,
      "rating": 0,
      "review_count": 0,
      "is_featured": false,
      "is_active": true
    },
    "images": [
      {
        "image_url": "6a0d92ab-0f92-49af-b1cd-43a7aa0b8e96.jpg",
        "alt_text": "XE MÁY ĐIỆN DIBAO PANSY S2 (CÀNG NHÔM)",
        "sort_order": 0,
        "is_primary": true
      },
      {
        "image_url": "4af7fccb-c16e-4b8b-80f8-5bc9cbf478f0.jpg",
        "alt_text": "XE MÁY ĐIỆN DIBAO PANSY S2 (CÀNG NHÔM)",
        "sort_order": 1,
        "is_primary": false
      },
      {
        "image_url": "d70c3d30-4a0f-4f63-a72d-dd2d44cd68be.jpg",
        "alt_text": "XE MÁY ĐIỆN DIBAO PANSY S2 (CÀNG NHÔM)",
        "sort_order": 2,
        "is_primary": false
      },
      {
        "image_url": "3acac2f3-0e6b-4162-b4b9-9203cb98c358.jpg",
        "alt_text": "XE MÁY ĐIỆN DIBAO PANSY S2 (CÀNG NHÔM)",
        "sort_order": 3,
        "is_primary": false
      },
      {
        "image_url": "e9bdd7d1-4a59-49b4-b9b6-a50e31417ee3.jpg",
        "alt_text": "XE MÁY ĐIỆN DIBAO PANSY S2 (CÀNG NHÔM)",
        "sort_order": 4,
        "is_primary": false
      }
    ],
    "variants": [
      {
        "sku": "xe-máy-điện-dibao-pansy-s2-càng-nhôm-default",
        "color": "",
        "size": "",
        "stock_quantity": 20
      }
    ]
  },
  {
    "category_slug": "xe-dap-dien",
    "product": {
      "name": "XE MÁY ĐIỆN DIBAO PANSY S4",
      "slug": "xe-máy-điện-dibao-pansy-s4",
      "description": "Tốc độ: 50 km/h | Công suất: 350 W | ắc quy 60v (5x12v) 22ah\n7\ntôc độ tối đa\n45-50km/h\n8\nquãng đường đi/lần xạc\n60-90km (tùy thuộc vào tốc độ di chuyển và tải trọng)\n9\nlốp xe\nlốp không săm 3",
      "price": 1299000013990000.0,
      "discount_price": null,
      "stock_quantity": 40,
      "rating": 0,
      "review_count": 0,
      "is_featured": false,
      "is_active": true
    },
    "images": [
      {
        "image_url": "20bbb328-c9bd-48f1-8a72-6b5d3253cf6d.jpg",
        "alt_text": "XE MÁY ĐIỆN DIBAO PANSY S4",
        "sort_order": 0,
        "is_primary": true
      },
      {
        "image_url": "520ea5f5-af20-44d1-a4e4-cd8f17a1d995.jpg",
        "alt_text": "XE MÁY ĐIỆN DIBAO PANSY S4",
        "sort_order": 1,
        "is_primary": false
      },
      {
        "image_url": "35f63f3e-b96c-427d-b7e8-e3708a300689.jpg",
        "alt_text": "XE MÁY ĐIỆN DIBAO PANSY S4",
        "sort_order": 2,
        "is_primary": false
      },
      {
        "image_url": "2d7b6c3f-4849-449e-97e0-4e77c0a40bee.jpg",
        "alt_text": "XE MÁY ĐIỆN DIBAO PANSY S4",
        "sort_order": 3,
        "is_primary": false
      },
      {
        "image_url": "13f44697-f3ba-4f95-a6ab-00ccb6227ae9.jpg",
        "alt_text": "XE MÁY ĐIỆN DIBAO PANSY S4",
        "sort_order": 4,
        "is_primary": false
      }
    ],
    "variants": [
      {
        "sku": "xe-máy-điện-dibao-pansy-s4-default",
        "color": "",
        "size": "",
        "stock_quantity": 20
      }
    ]
  },
  {
    "category_slug": "xe-dap-dien",
    "product": {
      "name": "XE MÁY ĐIỆN DIBAO CREER NILE",
      "slug": "xe-máy-điện-dibao-creer-nile",
      "description": "Tốc độ: 50 km/h | Công suất: 400 W | ắc quy chì a xít 60v (5x12v) 23ah\n7\ntôc độ tối đa:\n40-50km/h\n8\nquãng đường đi/lần xạc:\n60-90km (tùy thuộc vào tốc độ di chuyển và tải trọng)\n9\nlốp xe:\nlốp không săm 90/90-10\n10\nkiểu phanh:\nphanh đĩa trước",
      "price": 1299000013990000.0,
      "discount_price": null,
      "stock_quantity": 40,
      "rating": 0,
      "review_count": 0,
      "is_featured": false,
      "is_active": true
    },
    "images": [
      {
        "image_url": "532278e2-cef1-4c9c-9bb5-8bd79a8663d9.jpg",
        "alt_text": "XE MÁY ĐIỆN DIBAO CREER NILE",
        "sort_order": 0,
        "is_primary": true
      },
      {
        "image_url": "577ff3fc-2f65-4e1a-965b-854b9add0898.jpg",
        "alt_text": "XE MÁY ĐIỆN DIBAO CREER NILE",
        "sort_order": 1,
        "is_primary": false
      },
      {
        "image_url": "f007f019-bd89-4e40-971a-91a15e48d7d5.jpg",
        "alt_text": "XE MÁY ĐIỆN DIBAO CREER NILE",
        "sort_order": 2,
        "is_primary": false
      },
      {
        "image_url": "a1fc2a4c-8eeb-4b21-8b9e-38c2e2f55651.jpg",
        "alt_text": "XE MÁY ĐIỆN DIBAO CREER NILE",
        "sort_order": 3,
        "is_primary": false
      },
      {
        "image_url": "9d89bbaa-34c5-47ad-a36d-df2ae82fcf5a.jpg",
        "alt_text": "XE MÁY ĐIỆN DIBAO CREER NILE",
        "sort_order": 4,
        "is_primary": false
      }
    ],
    "variants": [
      {
        "sku": "xe-máy-điện-dibao-creer-nile-default",
        "color": "",
        "size": "",
        "stock_quantity": 20
      }
    ]
  },
  {
    "category_slug": "xe-dap-dien",
    "product": {
      "name": "XE MÁY ĐIỆN DIBAO PANSY DIO",
      "slug": "xe-máy-điện-dibao-pansy-dio",
      "description": "Tốc độ: 55 km/h | Công suất: 450 W | ắc quy 60v (5x12v) 22ah\n6 tôc độ 45-55km/h\n7 quãng đường đi/lần xạc 60km -90km (tùy theo tốc độ và tải trọng)\n8 lốp xe lốp không săm 90/90-10\n9 kiểu phanh phanh đĩa trước",
      "price": 1299000013990000.0,
      "discount_price": null,
      "stock_quantity": 40,
      "rating": 0,
      "review_count": 0,
      "is_featured": false,
      "is_active": true
    },
    "images": [
      {
        "image_url": "b9d5e3ad-5a4c-4890-8306-834b5d5aa6ff.jpg",
        "alt_text": "XE MÁY ĐIỆN DIBAO PANSY DIO",
        "sort_order": 0,
        "is_primary": true
      },
      {
        "image_url": "74bbb12b-e896-4113-b2a4-7e881a93e013.jpg",
        "alt_text": "XE MÁY ĐIỆN DIBAO PANSY DIO",
        "sort_order": 1,
        "is_primary": false
      },
      {
        "image_url": "9861ea90-df3c-46d5-92bd-af8d0e8c6f8e.jpg",
        "alt_text": "XE MÁY ĐIỆN DIBAO PANSY DIO",
        "sort_order": 2,
        "is_primary": false
      },
      {
        "image_url": "7e935307-6c6c-468c-9c5c-cc9334958d27.jpg",
        "alt_text": "XE MÁY ĐIỆN DIBAO PANSY DIO",
        "sort_order": 3,
        "is_primary": false
      },
      {
        "image_url": "e6062e71-c744-40fc-ac98-ce53c52928a5.jpg",
        "alt_text": "XE MÁY ĐIỆN DIBAO PANSY DIO",
        "sort_order": 4,
        "is_primary": false
      }
    ],
    "variants": [
      {
        "sku": "xe-máy-điện-dibao-pansy-dio-default",
        "color": "",
        "size": "",
        "stock_quantity": 20
      }
    ]
  },
  {
    "category_slug": "xe-dap-dien",
    "product": {
      "name": "XE MÁY ĐIỆN DIBAO TESLA DIO",
      "slug": "xe-máy-điện-dibao-tesla-dio",
      "description": "Tốc độ: 50 km/h | Công suất: 450 W | ắc quy 60v (5x12v) 22ah\n7 tôc độ 45-50km/h\n8 quãng đường đi/lần xạc 60km -90km (tùy theo tốc độ và tải trọng)\n9 lốp xe lốp không săm 90/90-10\n10 kiểu phanh phanh đĩa trước",
      "price": 1299000013990000.0,
      "discount_price": null,
      "stock_quantity": 40,
      "rating": 0,
      "review_count": 0,
      "is_featured": false,
      "is_active": true
    },
    "images": [
      {
        "image_url": "079225f2-9fce-4d49-b1c1-49b9ba4248e3.jpg",
        "alt_text": "XE MÁY ĐIỆN DIBAO TESLA DIO",
        "sort_order": 0,
        "is_primary": true
      },
      {
        "image_url": "ca4175ca-7091-4ffc-9d8a-d7015ba1b481.jpg",
        "alt_text": "XE MÁY ĐIỆN DIBAO TESLA DIO",
        "sort_order": 1,
        "is_primary": false
      },
      {
        "image_url": "1dc6e2e1-f882-48e0-a583-88e417cb852b.jpg",
        "alt_text": "XE MÁY ĐIỆN DIBAO TESLA DIO",
        "sort_order": 2,
        "is_primary": false
      },
      {
        "image_url": "cb5302a4-fc20-40b0-8a5c-9b47a5bcca91.jpg",
        "alt_text": "XE MÁY ĐIỆN DIBAO TESLA DIO",
        "sort_order": 3,
        "is_primary": false
      },
      {
        "image_url": "92a258c7-5b2b-4d44-8f9a-d559f198ba5d.jpg",
        "alt_text": "XE MÁY ĐIỆN DIBAO TESLA DIO",
        "sort_order": 4,
        "is_primary": false
      }
    ],
    "variants": [
      {
        "sku": "xe-máy-điện-dibao-tesla-dio-default",
        "color": "",
        "size": "",
        "stock_quantity": 20
      }
    ]
  },
  {
    "category_slug": "xe-dap-dien",
    "product": {
      "name": "XE MÁY ĐIỆN DIBAO RS 50CC",
      "slug": "xe-máy-điện-dibao-rs-50cc",
      "description": "Công suất: 100 W",
      "price": 1519000017590000.0,
      "discount_price": null,
      "stock_quantity": 40,
      "rating": 0,
      "review_count": 0,
      "is_featured": false,
      "is_active": true
    },
    "images": [
      {
        "image_url": "73631a77-c4f5-4c22-a0c4-6507c0a54c5d.jpg",
        "alt_text": "XE MÁY ĐIỆN DIBAO RS 50CC",
        "sort_order": 0,
        "is_primary": true
      },
      {
        "image_url": "739fd872-798d-4d46-9440-cb6811be1666.jpg",
        "alt_text": "XE MÁY ĐIỆN DIBAO RS 50CC",
        "sort_order": 1,
        "is_primary": false
      },
      {
        "image_url": "bf9f09a6-3aca-4a01-acbd-d1225ef877f0.jpg",
        "alt_text": "XE MÁY ĐIỆN DIBAO RS 50CC",
        "sort_order": 2,
        "is_primary": false
      },
      {
        "image_url": "4524fc10-bea4-4db1-a57b-f5381eae2fdd.jpg",
        "alt_text": "XE MÁY ĐIỆN DIBAO RS 50CC",
        "sort_order": 3,
        "is_primary": false
      },
      {
        "image_url": "16bd4204-046d-4bff-8107-b14fd8035641.jpg",
        "alt_text": "XE MÁY ĐIỆN DIBAO RS 50CC",
        "sort_order": 4,
        "is_primary": false
      }
    ],
    "variants": [
      {
        "sku": "xe-máy-điện-dibao-rs-50cc-default",
        "color": "",
        "size": "",
        "stock_quantity": 20
      }
    ]
  },
  {
    "category_slug": "xe-dap-dien",
    "product": {
      "name": "XE MÁY DIBAO SIR 50CC",
      "slug": "xe-máy-dibao-sir-50cc",
      "description": "Công suất: 100 W",
      "price": 1499000017390000.0,
      "discount_price": null,
      "stock_quantity": 40,
      "rating": 0,
      "review_count": 0,
      "is_featured": false,
      "is_active": true
    },
    "images": [
      {
        "image_url": "4cf9d36f-3c42-42d8-acb0-e89889aa169c.jpg",
        "alt_text": "XE MÁY DIBAO SIR 50CC",
        "sort_order": 0,
        "is_primary": true
      },
      {
        "image_url": "16ef4115-3a80-450b-adcc-bd2cfaa4a183.jpg",
        "alt_text": "XE MÁY DIBAO SIR 50CC",
        "sort_order": 1,
        "is_primary": false
      },
      {
        "image_url": "acd5c528-a8ab-4711-92b7-a36144ed06f5.jpg",
        "alt_text": "XE MÁY DIBAO SIR 50CC",
        "sort_order": 2,
        "is_primary": false
      },
      {
        "image_url": "f5b109db-60eb-48eb-8c33-77176b47401c.jpg",
        "alt_text": "XE MÁY DIBAO SIR 50CC",
        "sort_order": 3,
        "is_primary": false
      },
      {
        "image_url": "7b3c4210-e4a1-41e6-82e7-73b1d2346966.jpg",
        "alt_text": "XE MÁY DIBAO SIR 50CC",
        "sort_order": 4,
        "is_primary": false
      }
    ],
    "variants": [
      {
        "sku": "xe-máy-dibao-sir-50cc-default",
        "color": "",
        "size": "",
        "stock_quantity": 20
      }
    ]
  },
  {
    "category_slug": "xe-dap-dien",
    "product": {
      "name": "XE MÁY TAY GA 50CC DIBAO CREER",
      "slug": "xe-máy-tay-ga-50cc-dibao-creer",
      "description": "Công suất: 600 W",
      "price": 1945000021690000.0,
      "discount_price": null,
      "stock_quantity": 40,
      "rating": 0,
      "review_count": 0,
      "is_featured": false,
      "is_active": true
    },
    "images": [
      {
        "image_url": "43acd0e2-5bdd-48f5-bbd7-fc7528be8711.jpg",
        "alt_text": "XE MÁY TAY GA 50CC DIBAO CREER",
        "sort_order": 0,
        "is_primary": true
      },
      {
        "image_url": "1ec726bf-39fa-49f6-8cc5-b4a03a34e415.jpg",
        "alt_text": "XE MÁY TAY GA 50CC DIBAO CREER",
        "sort_order": 1,
        "is_primary": false
      },
      {
        "image_url": "5eb768a0-ad7f-4453-9673-2c8d4197cb68.jpg",
        "alt_text": "XE MÁY TAY GA 50CC DIBAO CREER",
        "sort_order": 2,
        "is_primary": false
      },
      {
        "image_url": "67613d5a-3440-4f07-ac91-bf72fe9df850.jpg",
        "alt_text": "XE MÁY TAY GA 50CC DIBAO CREER",
        "sort_order": 3,
        "is_primary": false
      },
      {
        "image_url": "63a45cef-732a-483a-8ad9-3072c22aa442.jpg",
        "alt_text": "XE MÁY TAY GA 50CC DIBAO CREER",
        "sort_order": 4,
        "is_primary": false
      }
    ],
    "variants": [
      {
        "sku": "xe-máy-tay-ga-50cc-dibao-creer-default",
        "color": "",
        "size": "",
        "stock_quantity": 20
      }
    ]
  },
  {
    "category_slug": "xe-dap-dien",
    "product": {
      "name": "XE MÁY TAY GA 50CC DIBAO PANSY XS1 (BẢN NÂNG CẤP)",
      "slug": "xe-máy-tay-ga-50cc-dibao-pansy-xs1-bản-nâng-cấp",
      "description": "Công suất: 600 W",
      "price": 1945000021690000.0,
      "discount_price": null,
      "stock_quantity": 40,
      "rating": 0,
      "review_count": 0,
      "is_featured": false,
      "is_active": true
    },
    "images": [
      {
        "image_url": "618841f9-2b52-4fdf-87cb-8a0e8ac9c311.jpg",
        "alt_text": "XE MÁY TAY GA 50CC DIBAO PANSY XS1 (BẢN NÂNG CẤP)",
        "sort_order": 0,
        "is_primary": true
      },
      {
        "image_url": "f04c67b1-6075-4c82-ba70-3aa9b31f57a6.jpg",
        "alt_text": "XE MÁY TAY GA 50CC DIBAO PANSY XS1 (BẢN NÂNG CẤP)",
        "sort_order": 1,
        "is_primary": false
      },
      {
        "image_url": "64734e72-ac6b-4b51-b9b5-09318bdd4ac3.jpg",
        "alt_text": "XE MÁY TAY GA 50CC DIBAO PANSY XS1 (BẢN NÂNG CẤP)",
        "sort_order": 2,
        "is_primary": false
      },
      {
        "image_url": "eac394ac-9c9f-4a1a-9c4e-4303e693f6c1.jpg",
        "alt_text": "XE MÁY TAY GA 50CC DIBAO PANSY XS1 (BẢN NÂNG CẤP)",
        "sort_order": 3,
        "is_primary": false
      },
      {
        "image_url": "e1f19ff4-9b0a-4434-a57c-9d1c278e2504.jpg",
        "alt_text": "XE MÁY TAY GA 50CC DIBAO PANSY XS1 (BẢN NÂNG CẤP)",
        "sort_order": 4,
        "is_primary": false
      }
    ],
    "variants": [
      {
        "sku": "xe-máy-tay-ga-50cc-dibao-pansy-xs1-bản-nâng-cấp-default",
        "color": "",
        "size": "",
        "stock_quantity": 20
      }
    ]
  },
  {
    "category_slug": "xe-dap-dien",
    "product": {
      "name": "Xe tay ga 50cc DIBAO Tesla X",
      "slug": "xe-tay-ga-50cc-dibao-tesla-x",
      "description": "",
      "price": 2639000026990000.0,
      "discount_price": null,
      "stock_quantity": 40,
      "rating": 0,
      "review_count": 0,
      "is_featured": false,
      "is_active": true
    },
    "images": [
      {
        "image_url": "34516336-227e-4ea8-908f-9be613e7ac02.jpg",
        "alt_text": "Xe tay ga 50cc DIBAO Tesla X",
        "sort_order": 0,
        "is_primary": true
      },
      {
        "image_url": "ba943b12-9b32-425e-a9e2-b0af161b01c8.jpg",
        "alt_text": "Xe tay ga 50cc DIBAO Tesla X",
        "sort_order": 1,
        "is_primary": false
      },
      {
        "image_url": "10b82129-16ee-412d-bed8-113528aab3ce.jpg",
        "alt_text": "Xe tay ga 50cc DIBAO Tesla X",
        "sort_order": 2,
        "is_primary": false
      },
      {
        "image_url": "de85142e-81a5-4195-8293-50ab06f90eac.jpg",
        "alt_text": "Xe tay ga 50cc DIBAO Tesla X",
        "sort_order": 3,
        "is_primary": false
      },
      {
        "image_url": "1c2ff5e4-73fb-4790-aee5-ca16914db09e.jpg",
        "alt_text": "Xe tay ga 50cc DIBAO Tesla X",
        "sort_order": 4,
        "is_primary": false
      }
    ],
    "variants": [
      {
        "sku": "xe-tay-ga-50cc-dibao-tesla-x-default",
        "color": "",
        "size": "",
        "stock_quantity": 20
      }
    ]
  },
  {
    "category_slug": "xe-dap-dien",
    "product": {
      "name": "XE MÁY TAY GA DIBAO PANSY XS1",
      "slug": "xe-máy-tay-ga-dibao-pansy-xs1",
      "description": "Công suất: 600 W",
      "price": 1945000021690000.0,
      "discount_price": null,
      "stock_quantity": 40,
      "rating": 0,
      "review_count": 0,
      "is_featured": false,
      "is_active": true
    },
    "images": [
      {
        "image_url": "5c2b84ff-de63-469c-97cf-76764f872bc6.jpg",
        "alt_text": "XE MÁY TAY GA DIBAO PANSY XS1",
        "sort_order": 0,
        "is_primary": true
      },
      {
        "image_url": "a3e11349-34a8-455f-9b19-31b7a28bb9a5.jpg",
        "alt_text": "XE MÁY TAY GA DIBAO PANSY XS1",
        "sort_order": 1,
        "is_primary": false
      },
      {
        "image_url": "1fdf1e77-1742-4f87-94bc-de76682e28e4.jpg",
        "alt_text": "XE MÁY TAY GA DIBAO PANSY XS1",
        "sort_order": 2,
        "is_primary": false
      },
      {
        "image_url": "17412b8a-62c0-4d24-bd56-41e371a0dc60.jpg",
        "alt_text": "XE MÁY TAY GA DIBAO PANSY XS1",
        "sort_order": 3,
        "is_primary": false
      },
      {
        "image_url": "876f557f-ebbb-44ce-a279-2c627ccd3798.jpg",
        "alt_text": "XE MÁY TAY GA DIBAO PANSY XS1",
        "sort_order": 4,
        "is_primary": false
      }
    ],
    "variants": [
      {
        "sku": "xe-máy-tay-ga-dibao-pansy-xs1-default",
        "color": "",
        "size": "",
        "stock_quantity": 20
      }
    ]
  },
  {
    "category_slug": "xe-dap-dien",
    "product": {
      "name": "XE MÁY TAY GA DIBAO PANSY XS",
      "slug": "xe-máy-tay-ga-dibao-pansy-xs",
      "description": "Công suất: 600 W",
      "price": 1945000021690000.0,
      "discount_price": null,
      "stock_quantity": 40,
      "rating": 0,
      "review_count": 0,
      "is_featured": false,
      "is_active": true
    },
    "images": [
      {
        "image_url": "603d850f-38b6-43cf-8cfd-eda65a4eade8.jpg",
        "alt_text": "XE MÁY TAY GA DIBAO PANSY XS",
        "sort_order": 0,
        "is_primary": true
      },
      {
        "image_url": "c3af0609-43d7-4d63-bd45-4666fbaddba5.jpg",
        "alt_text": "XE MÁY TAY GA DIBAO PANSY XS",
        "sort_order": 1,
        "is_primary": false
      },
      {
        "image_url": "eaa68a45-ceba-4d58-a97e-0d23e5bbceed.jpg",
        "alt_text": "XE MÁY TAY GA DIBAO PANSY XS",
        "sort_order": 2,
        "is_primary": false
      },
      {
        "image_url": "05be52ba-7dfc-4135-bea3-0773dfb1dd35.jpg",
        "alt_text": "XE MÁY TAY GA DIBAO PANSY XS",
        "sort_order": 3,
        "is_primary": false
      },
      {
        "image_url": "f13fe86d-6cb9-4211-a914-18bc6be38198.jpg",
        "alt_text": "XE MÁY TAY GA DIBAO PANSY XS",
        "sort_order": 4,
        "is_primary": false
      }
    ],
    "variants": [
      {
        "sku": "xe-máy-tay-ga-dibao-pansy-xs-default",
        "color": "",
        "size": "",
        "stock_quantity": 20
      }
    ]
  },
  {
    "category_slug": "xe-dap-dien",
    "product": {
      "name": "XE MÁY TAY GA 50CC DIBAO GOFAST",
      "slug": "xe-máy-tay-ga-50cc-dibao-gofast",
      "description": "Công suất: 200 W",
      "price": 1945000021690000.0,
      "discount_price": null,
      "stock_quantity": 40,
      "rating": 0,
      "review_count": 0,
      "is_featured": false,
      "is_active": true
    },
    "images": [
      {
        "image_url": "6e4f5e89-9f5b-4ea8-bb13-97fc3f510c0c.jpg",
        "alt_text": "XE MÁY TAY GA 50CC DIBAO GOFAST",
        "sort_order": 0,
        "is_primary": true
      },
      {
        "image_url": "c8679d1c-ccb5-42db-9007-95c3c2996a40.jpg",
        "alt_text": "XE MÁY TAY GA 50CC DIBAO GOFAST",
        "sort_order": 1,
        "is_primary": false
      },
      {
        "image_url": "5f831023-01b1-48cf-ada3-f8f8f2baf0b0.jpg",
        "alt_text": "XE MÁY TAY GA 50CC DIBAO GOFAST",
        "sort_order": 2,
        "is_primary": false
      },
      {
        "image_url": "e5d483af-20b1-4f46-a9ae-880c413bf713.jpg",
        "alt_text": "XE MÁY TAY GA 50CC DIBAO GOFAST",
        "sort_order": 3,
        "is_primary": false
      },
      {
        "image_url": "9b6627b1-f2c0-41bc-b883-0b128fbaa9c8.jpg",
        "alt_text": "XE MÁY TAY GA 50CC DIBAO GOFAST",
        "sort_order": 4,
        "is_primary": false
      }
    ],
    "variants": [
      {
        "sku": "xe-máy-tay-ga-50cc-dibao-gofast-default",
        "color": "",
        "size": "",
        "stock_quantity": 20
      }
    ]
  }
]